[
  {
    "titulo": "Pneu 205/55r16 Goodyear Eagle Sport 2 91v Aro 16 Índice de velocidade V",
    "link": "https://www.mercadolivre.com.br/pneu-20555r16-goodyear-eagle-sport-2-91v-aro-16-indice-de-velocidade-v/p/MLB28688467",
    "preco": 513.98,
    "query_strict": "",
    "size_norm": "",
    "brand_expected": "",
    "line_expected": "",
    "size_ok": true,
    "free_ship": true,
    "frete": 0.0,
    "local": "",
    "vendedor": "",
    "condicao": "Novo",
    "frete_gratis": true,
    "marketplace": "mercadolivre",
    "marca": "goodyear",
    "data_coleta": "2025-08-08 16:47:36",
    "preco_original": null,
    "preco_desconto": 513.98,
    "desconto_pct": null,
    "shipping": {}
  },
  {
    "titulo": "Pneu Goodyear Direction Sport 2 Aro 16 205/55r16 91v Índice De Velocidade V",
    "link": "https://www.mercadolivre.com.br/pneu-goodyear-direction-sport-2-aro-16-20555r16-91v-indice-de-velocidade-v/p/MLB36719920",
    "preco": 498.85,
    "query_strict": "",
    "size_norm": "",
    "brand_expected": "",
    "line_expected": "",
    "size_ok": true,
    "free_ship": false,
    "frete": null,
    "local": "",
    "vendedor": "",
    "condicao": "Novo",
    "frete_gratis": false,
    "marketplace": "mercadolivre",
    "marca": "goodyear",
    "data_coleta": "2025-08-08 16:47:38",
    "preco_original": null,
    "preco_desconto": 498.85,
    "desconto_pct": null,
    "shipping": {}
  },
  {
    "titulo": "Pneu 205/55r16 Goodyear Eagle Sport 2 91v Aro 16",
    "link": "https://produto.mercadolivre.com.br/MLB-2088021683-pneu-20555r16-goodyear-eagle-sport-2-91v-aro-16-_JM?searchVariation=173917610473",
    "preco": 659.89,
    "query_strict": "",
    "size_norm": "",
    "brand_expected": "",
    "line_expected": "",
    "size_ok": true,
    "free_ship": true,
    "frete": 0.0,
    "local": "",
    "vendedor": "",
    "condicao": "Novo",
    "frete_gratis": true,
    "marketplace": "mercadolivre",
    "marca": "goodyear",
    "data_coleta": "2025-08-08 16:47:39",
    "preco_original": null,
    "preco_desconto": 659.89,
    "desconto_pct": null,
    "shipping": {}
  },
  {
    "titulo": "Pneu Goodyear Aro 16 Eagle Sport 2 205/55r16 91v",
    "link": "https://www.mercadolivre.com.br/pneu-goodyear-aro-16-eagle-sport-2-20555r16-91v/up/MLBU1134847785",
    "preco": 580.28,
    "query_strict": "",
    "size_norm": "",
    "brand_expected": "",
    "line_expected": "",
    "size_ok": true,
    "free_ship": true,
    "frete": 0.0,
    "local": "",
    "vendedor": "",
    "condicao": "Novo",
    "frete_gratis": true,
    "marketplace": "mercadolivre",
    "marca": "goodyear",
    "data_coleta": "2025-08-08 16:47:41",
    "preco_original": null,
    "preco_desconto": 580.28,
    "desconto_pct": null,
    "shipping": {}
  },
  {
    "titulo": "Pneu Goodyear Eagle Sport P 205/55R16 91 V",
    "link": "https://www.mercadolivre.com.br/pneu-goodyear-eagle-sport-p-20555r16-91-v/p/MLB14862366",
    "preco": 746.95,
    "query_strict": "",
    "size_norm": "",
    "brand_expected": "",
    "line_expected": "",
    "size_ok": true,
    "free_ship": true,
    "frete": 0.0,
    "local": "",
    "vendedor": "",
    "condicao": "Novo",
    "frete_gratis": true,
    "marketplace": "mercadolivre",
    "marca": "goodyear",
    "data_coleta": "2025-08-08 16:47:42",
    "preco_original": null,
    "preco_desconto": 746.95,
    "desconto_pct": null,
    "shipping": {}
  },
  {
    "titulo": "Pneu Aro 16 Goodyear 205/55r16 Eagle Sport 2 Focus Stilo Bmw",
    "link": "https://produto.mercadolivre.com.br/MLB-2070640674-pneu-aro-16-goodyear-20555r16-eagle-sport-2-focus-stilo-bmw-_JM",
    "preco": 790.99,
    "query_strict": "",
    "size_norm": "",
    "brand_expected": "",
    "line_expected": "",
    "size_ok": true,
    "free_ship": true,
    "frete": 0.0,
    "local": "",
    "vendedor": "",
    "condicao": "Novo",
    "frete_gratis": true,
    "marketplace": "mercadolivre",
    "marca": "goodyear",
    "data_coleta": "2025-08-08 16:47:44",
    "preco_original": null,
    "preco_desconto": 790.99,
    "desconto_pct": null,
    "shipping": {}
  },
  {
    "titulo": "Pneu Aro 16 Goodyear 205/55r16 Eagle Sport 2 91v",
    "link": "https://produto.mercadolivre.com.br/MLB-2070589354-pneu-aro-16-goodyear-20555r16-eagle-sport-2-91v-_JM",
    "preco": 594.51,
    "query_strict": "",
    "size_norm": "",
    "brand_expected": "",
    "line_expected": "",
    "size_ok": true,
    "free_ship": true,
    "frete": 0.0,
    "local": "",
    "vendedor": "",
    "condicao": "Novo",
    "frete_gratis": true,
    "marketplace": "mercadolivre",
    "marca": "goodyear",
    "data_coleta": "2025-08-08 16:47:46",
    "preco_original": null,
    "preco_desconto": 594.51,
    "desconto_pct": null,
    "shipping": {}
  },
  {
    "titulo": "Pneu Goodyear Aro 16 Eagle Sport 2 205/55r16 91v",
    "link": "https://www.mercadolivre.com.br/pneu-goodyear-aro-16-eagle-sport-2-20555r16-91v/up/MLBU3233185996",
    "preco": 543.5,
    "query_strict": "",
    "size_norm": "",
    "brand_expected": "",
    "line_expected": "",
    "size_ok": true,
    "free_ship": true,
    "frete": 0.0,
    "local": "",
    "vendedor": "",
    "condicao": "Novo",
    "frete_gratis": true,
    "marketplace": "mercadolivre",
    "marca": "goodyear",
    "data_coleta": "2025-08-08 16:47:48",
    "preco_original": null,
    "preco_desconto": 543.5,
    "desconto_pct": null,
    "shipping": {}
  },
  {
    "titulo": "Pneu Goodyear Eagle Sport 205/55 R16 91 Sl - 1 Unid.",
    "link": "https://produto.mercadolivre.com.br/MLB-5002355776-pneu-goodyear-eagle-sport-20555-r16-91-sl-1-unid-_JM?searchVariation=184309967281",
    "preco": 707.55,
    "query_strict": "",
    "size_norm": "",
    "brand_expected": "",
    "line_expected": "",
    "size_ok": true,
    "free_ship": true,
    "frete": 0.0,
    "local": "",
    "vendedor": "",
    "condicao": "Novo",
    "frete_gratis": true,
    "marketplace": "mercadolivre",
    "marca": "goodyear",
    "data_coleta": "2025-08-08 16:47:49",
    "preco_original": null,
    "preco_desconto": 707.55,
    "desconto_pct": null,
    "shipping": {}
  },
  {
    "titulo": "Pneu Golf Aro 16 205/55r16 Eagle Sport 2 91v Goodyear",
    "link": "https://produto.mercadolivre.com.br/MLB-2070646822-pneu-golf-aro-16-20555r16-eagle-sport-2-91v-goodyear-_JM",
    "preco": 742.99,
    "query_strict": "",
    "size_norm": "",
    "brand_expected": "",
    "line_expected": "",
    "size_ok": true,
    "free_ship": true,
    "frete": 0.0,
    "local": "",
    "vendedor": "",
    "condicao": "Novo",
    "frete_gratis": true,
    "marketplace": "mercadolivre",
    "marca": "goodyear",
    "data_coleta": "2025-08-08 16:47:51",
    "preco_original": null,
    "preco_desconto": 742.99,
    "desconto_pct": null,
    "shipping": {}
  },
  {
    "titulo": "Pneu Goodyear 205 55 R16 Eagle Sport 2 91 V",
    "link": "https://produto.mercadolivre.com.br/MLB-4056687249-pneu-goodyear-205-55-r16-eagle-sport-2-91-v-_JM",
    "preco": 711.33,
    "query_strict": "",
    "size_norm": "",
    "brand_expected": "",
    "line_expected": "",
    "size_ok": true,
    "free_ship": true,
    "frete": 0.0,
    "local": "",
    "vendedor": "",
    "condicao": "Novo",
    "frete_gratis": true,
    "marketplace": "mercadolivre",
    "marca": "goodyear",
    "data_coleta": "2025-08-08 16:47:53",
    "preco_original": null,
    "preco_desconto": 711.33,
    "desconto_pct": null,
    "shipping": {}
  },
  {
    "titulo": "Pneu Goodyear 205/55r16 Eagle Sport 2 91v Audi A3 A4 Vectra",
    "link": "https://produto.mercadolivre.com.br/MLB-2070615090-pneu-goodyear-20555r16-eagle-sport-2-91v-audi-a3-a4-vectra-_JM",
    "preco": 666.6,
    "query_strict": "",
    "size_norm": "",
    "brand_expected": "",
    "line_expected": "",
    "size_ok": true,
    "free_ship": true,
    "frete": 0.0,
    "local": "",
    "vendedor": "",
    "condicao": "Novo",
    "frete_gratis": true,
    "marketplace": "mercadolivre",
    "marca": "goodyear",
    "data_coleta": "2025-08-08 16:47:54",
    "preco_original": null,
    "preco_desconto": 666.6,
    "desconto_pct": null,
    "shipping": {}
  },
  {
    "titulo": "Pneu 205/55r16 Eagle Sport 2 91v Goodyear",
    "link": "https://produto.mercadolivre.com.br/MLB-2070645939-pneu-20555r16-eagle-sport-2-91v-goodyear-_JM",
    "preco": 591.32,
    "query_strict": "",
    "size_norm": "",
    "brand_expected": "",
    "line_expected": "",
    "size_ok": true,
    "free_ship": true,
    "frete": 0.0,
    "local": "",
    "vendedor": "",
    "condicao": "Novo",
    "frete_gratis": true,
    "marketplace": "mercadolivre",
    "marca": "goodyear",
    "data_coleta": "2025-08-08 16:47:56",
    "preco_original": null,
    "preco_desconto": 591.32,
    "desconto_pct": null,
    "shipping": {}
  },
  {
    "titulo": "Pneu 205/55r16 Goodyear Eagle Sport 2 91v Aro 16",
    "link": "https://produto.mercadolivre.com.br/MLB-2087991375-pneu-20555r16-goodyear-eagle-sport-2-91v-aro-16-_JM?searchVariation=173917641986",
    "preco": 609.89,
    "query_strict": "",
    "size_norm": "",
    "brand_expected": "",
    "line_expected": "",
    "size_ok": true,
    "free_ship": true,
    "frete": 0.0,
    "local": "",
    "vendedor": "",
    "condicao": "Novo",
    "frete_gratis": true,
    "marketplace": "mercadolivre",
    "marca": "goodyear",
    "data_coleta": "2025-08-08 16:47:57",
    "preco_original": null,
    "preco_desconto": 609.89,
    "desconto_pct": null,
    "shipping": {}
  },
  {
    "titulo": "Pneu Golf Aro 16 205/55r16 Eagle Sport 2 91v Goodyear",
    "link": "https://produto.mercadolivre.com.br/MLB-2070583172-pneu-golf-aro-16-20555r16-eagle-sport-2-91v-goodyear-_JM",
    "preco": 633.67,
    "query_strict": "",
    "size_norm": "",
    "brand_expected": "",
    "line_expected": "",
    "size_ok": true,
    "free_ship": true,
    "frete": 0.0,
    "local": "",
    "vendedor": "",
    "condicao": "Novo",
    "frete_gratis": true,
    "marketplace": "mercadolivre",
    "marca": "goodyear",
    "data_coleta": "2025-08-08 16:47:59",
    "preco_original": null,
    "preco_desconto": 633.67,
    "desconto_pct": null,
    "shipping": {}
  },
  {
    "titulo": "Pneu Aro 16 Goodyear 205/55 R16 91v Eagle Sport 2 Sl",
    "link": "https://produto.mercadolivre.com.br/MLB-5301994190-pneu-aro-16-goodyear-20555-r16-91v-eagle-sport-2-sl-_JM",
    "preco": 547.11,
    "query_strict": "",
    "size_norm": "",
    "brand_expected": "",
    "line_expected": "",
    "size_ok": true,
    "free_ship": true,
    "frete": 0.0,
    "local": "",
    "vendedor": "",
    "condicao": "Novo",
    "frete_gratis": true,
    "marketplace": "mercadolivre",
    "marca": "goodyear",
    "data_coleta": "2025-08-08 16:48:00",
    "preco_original": null,
    "preco_desconto": 547.11,
    "desconto_pct": null,
    "shipping": {}
  },
  {
    "titulo": "Pneu Goodyear 205/55r16 Eagle Sport 2 91v Aro 16",
    "link": "https://produto.mercadolivre.com.br/MLB-2070646794-pneu-goodyear-20555r16-eagle-sport-2-91v-aro-16-_JM",
    "preco": 594.51,
    "query_strict": "",
    "size_norm": "",
    "brand_expected": "",
    "line_expected": "",
    "size_ok": true,
    "free_ship": true,
    "frete": 0.0,
    "local": "",
    "vendedor": "",
    "condicao": "Novo",
    "frete_gratis": true,
    "marketplace": "mercadolivre",
    "marca": "goodyear",
    "data_coleta": "2025-08-08 16:48:01",
    "preco_original": null,
    "preco_desconto": 594.51,
    "desconto_pct": null,
    "shipping": {}
  },
  {
    "titulo": "Pneu Aro 16 Goodyear 205/55r16 Eagle Sport 2 Megane Corolla",
    "link": "https://produto.mercadolivre.com.br/MLB-2070589382-pneu-aro-16-goodyear-20555r16-eagle-sport-2-megane-corolla-_JM",
    "preco": 666.6,
    "query_strict": "",
    "size_norm": "",
    "brand_expected": "",
    "line_expected": "",
    "size_ok": true,
    "free_ship": true,
    "frete": 0.0,
    "local": "",
    "vendedor": "",
    "condicao": "Novo",
    "frete_gratis": true,
    "marketplace": "mercadolivre",
    "marca": "goodyear",
    "data_coleta": "2025-08-08 16:48:03",
    "preco_original": null,
    "preco_desconto": 666.6,
    "desconto_pct": null,
    "shipping": {}
  },
  {
    "titulo": "Pneu Goodyear 205/55r16 Eagle Sport 2 91v Aro 16",
    "link": "https://produto.mercadolivre.com.br/MLB-2070615075-pneu-goodyear-20555r16-eagle-sport-2-91v-aro-16-_JM",
    "preco": 637.16,
    "query_strict": "",
    "size_norm": "",
    "brand_expected": "",
    "line_expected": "",
    "size_ok": true,
    "free_ship": true,
    "frete": 0.0,
    "local": "",
    "vendedor": "",
    "condicao": "Novo",
    "frete_gratis": true,
    "marketplace": "mercadolivre",
    "marca": "goodyear",
    "data_coleta": "2025-08-08 16:48:05",
    "preco_original": null,
    "preco_desconto": 637.16,
    "desconto_pct": null,
    "shipping": {}
  },
  {
    "titulo": "Pneu Aro 16 Goodyear 205/55 R16 91v Eagle Sport 2 Sl",
    "link": "https://produto.mercadolivre.com.br/MLB-5302057346-pneu-aro-16-goodyear-20555-r16-91v-eagle-sport-2-sl-_JM",
    "preco": 579.86,
    "query_strict": "",
    "size_norm": "",
    "brand_expected": "",
    "line_expected": "",
    "size_ok": true,
    "free_ship": true,
    "frete": 0.0,
    "local": "",
    "vendedor": "",
    "condicao": "Novo",
    "frete_gratis": true,
    "marketplace": "mercadolivre",
    "marca": "goodyear",
    "data_coleta": "2025-08-08 16:48:06",
    "preco_original": null,
    "preco_desconto": 579.86,
    "desconto_pct": null,
    "shipping": {}
  },
  {
    "titulo": "Pneu Aro 16 Goodyear 205/55r16 Eagle Sport 2 Megane Corolla",
    "link": "https://produto.mercadolivre.com.br/MLB-2070640625-pneu-aro-16-goodyear-20555r16-eagle-sport-2-megane-corolla-_JM",
    "preco": 625.66,
    "query_strict": "",
    "size_norm": "",
    "brand_expected": "",
    "line_expected": "",
    "size_ok": true,
    "free_ship": true,
    "frete": 0.0,
    "local": "",
    "vendedor": "",
    "condicao": "Novo",
    "frete_gratis": true,
    "marketplace": "mercadolivre",
    "marca": "goodyear",
    "data_coleta": "2025-08-08 16:48:07",
    "preco_original": null,
    "preco_desconto": 625.66,
    "desconto_pct": null,
    "shipping": {}
  },
  {
    "titulo": "Pneu Delinte 205/55/16 94w Xl Dh2 Frete Grátis* V",
    "link": "https://www.mercadolivre.com.br/pneu-delinte-2055516-94w-xl-dh2-frete-gratis/up/MLBU1718460344",
    "preco": 707.56,
    "query_strict": "",
    "size_norm": "",
    "brand_expected": "",
    "line_expected": "",
    "size_ok": true,
    "free_ship": true,
    "frete": 0.0,
    "local": "",
    "vendedor": "",
    "condicao": "Novo",
    "frete_gratis": true,
    "marketplace": "mercadolivre",
    "marca": "",
    "data_coleta": "2025-08-08 16:49:37",
    "preco_original": null,
    "preco_desconto": 707.56,
    "desconto_pct": null,
    "shipping": {}
  },
  {
    "titulo": "Pneu Goodyear Aro 16 Eagle Sport 2 205/55r16 91v A3",
    "link": "https://www.mercadolivre.com.br/pneu-goodyear-aro-16-eagle-sport-2-20555r16-91v/up/MLBU1419668054",
    "preco": 499.0,
    "query_strict": "",
    "size_norm": "",
    "brand_expected": "",
    "line_expected": "",
    "size_ok": true,
    "free_ship": true,
    "frete": 0.0,
    "local": "",
    "vendedor": "",
    "condicao": "Novo",
    "frete_gratis": true,
    "marketplace": "mercadolivre",
    "marca": "goodyear",
    "data_coleta": "2025-08-08 16:49:38",
    "preco_original": null,
    "preco_desconto": 499.0,
    "desconto_pct": null,
    "shipping": {}
  },
  {
    "titulo": "Pneu Goodyear Aro 16 Eagle Sport 2 205/55r16 91v A3",
    "link": "https://www.mercadolivre.com.br/pneu-goodyear-aro-16-eagle-sport-2-20555r16-91v/up/MLBU1415672895",
    "preco": 509.16,
    "query_strict": "",
    "size_norm": "",
    "brand_expected": "",
    "line_expected": "",
    "size_ok": true,
    "free_ship": true,
    "frete": 0.0,
    "local": "",
    "vendedor": "",
    "condicao": "Novo",
    "frete_gratis": true,
    "marketplace": "mercadolivre",
    "marca": "goodyear",
    "data_coleta": "2025-08-08 16:49:40",
    "preco_original": null,
    "preco_desconto": 509.16,
    "desconto_pct": null,
    "shipping": {}
  },
  {
    "titulo": "Pneu Goodyear Aro 16 Eagle Sport 2 205/55r16 91v",
    "link": "https://www.mercadolivre.com.br/pneu-goodyear-aro-16-eagle-sport-2-20555r16-91v/up/MLBU792696443",
    "preco": 534.3,
    "query_strict": "",
    "size_norm": "",
    "brand_expected": "",
    "line_expected": "",
    "size_ok": true,
    "free_ship": true,
    "frete": 0.0,
    "local": "",
    "vendedor": "",
    "condicao": "Novo",
    "frete_gratis": true,
    "marketplace": "mercadolivre",
    "marca": "goodyear",
    "data_coleta": "2025-08-08 16:49:42",
    "preco_original": null,
    "preco_desconto": 534.3,
    "desconto_pct": null,
    "shipping": {}
  },
  {
    "titulo": "Pneu 205/55r16 Goodyear Eagle Sport 2 91v Sl V",
    "link": "https://www.mercadolivre.com.br/pneu-20555r16-goodyear-eagle-sport-2-91v-sl/up/MLBU1130316253",
    "preco": 639.07,
    "query_strict": "",
    "size_norm": "",
    "brand_expected": "",
    "line_expected": "",
    "size_ok": true,
    "free_ship": true,
    "frete": 0.0,
    "local": "",
    "vendedor": "",
    "condicao": "Novo",
    "frete_gratis": true,
    "marketplace": "mercadolivre",
    "marca": "goodyear",
    "data_coleta": "2025-08-08 16:49:44",
    "preco_original": null,
    "preco_desconto": 639.07,
    "desconto_pct": null,
    "shipping": {}
  },
  {
    "titulo": "Pneu 205/55r16 Goodyear Eagle Sport 2 91v Sl V",
    "link": "https://www.mercadolivre.com.br/pneu-20555r16-goodyear-eagle-sport-2-91v-sl/up/MLBU3039399798",
    "preco": 653.31,
    "query_strict": "",
    "size_norm": "",
    "brand_expected": "",
    "line_expected": "",
    "size_ok": true,
    "free_ship": true,
    "frete": 0.0,
    "local": "",
    "vendedor": "",
    "condicao": "Novo",
    "frete_gratis": true,
    "marketplace": "mercadolivre",
    "marca": "goodyear",
    "data_coleta": "2025-08-08 16:49:45",
    "preco_original": null,
    "preco_desconto": 653.31,
    "desconto_pct": null,
    "shipping": {}
  },
  {
    "titulo": "Pneu 205/55r16 Goodyear Eagle Sport 2 91v",
    "link": "https://produto.mercadolivre.com.br/MLB-4132880633-pneu-20555r16-goodyear-eagle-sport-2-91v-_JM?searchVariation=189147065795",
    "preco": 157.5,
    "query_strict": "",
    "size_norm": "",
    "brand_expected": "",
    "line_expected": "",
    "size_ok": true,
    "free_ship": false,
    "frete": null,
    "local": "",
    "vendedor": "",
    "condicao": "Novo",
    "frete_gratis": false,
    "marketplace": "mercadolivre",
    "marca": "goodyear",
    "data_coleta": "2025-08-08 16:49:47",
    "preco_original": null,
    "preco_desconto": 157.5,
    "desconto_pct": null,
    "shipping": {}
  },
  {
    "titulo": "Pneu Goodyear Eagle Sport P 205/55r16 91 V",
    "link": "https://produto.mercadolivre.com.br/MLB-3077438148-pneu-goodyear-eagle-sport-p-20555r16-91-v-_JM?searchVariation=176205044551",
    "preco": 299.0,
    "query_strict": "",
    "size_norm": "",
    "brand_expected": "",
    "line_expected": "",
    "size_ok": true,
    "free_ship": false,
    "frete": null,
    "local": "",
    "vendedor": "",
    "condicao": "Novo",
    "frete_gratis": false,
    "marketplace": "mercadolivre",
    "marca": "goodyear",
    "data_coleta": "2025-08-08 16:49:49",
    "preco_original": null,
    "preco_desconto": 299.0,
    "desconto_pct": null,
    "shipping": {}
  },
  {
    "titulo": "Pneu Vucanizado Goodyear Eagle Sport 2 205/55 R16 91v",
    "link": "https://produto.mercadolivre.com.br/MLB-4012853745-pneu-vucanizado-goodyear-eagle-sport-2-20555-r16-91v-_JM?searchVariation=187320941279",
    "preco": 230.0,
    "query_strict": "",
    "size_norm": "",
    "brand_expected": "",
    "line_expected": "",
    "size_ok": true,
    "free_ship": false,
    "frete": null,
    "local": "",
    "vendedor": "",
    "condicao": "Novo",
    "frete_gratis": false,
    "marketplace": "mercadolivre",
    "marca": "goodyear",
    "data_coleta": "2025-08-08 16:49:50",
    "preco_original": null,
    "preco_desconto": 230.0,
    "desconto_pct": null,
    "shipping": {}
  },
  {
    "titulo": "Pneu Goodyear Eagle Sport 205/55r16",
    "link": "https://produto.mercadolivre.com.br/MLB-3079915662-pneu-goodyear-eagle-sport-20555r16-_JM?searchVariation=176211635658",
    "preco": 249.0,
    "query_strict": "",
    "size_norm": "",
    "brand_expected": "",
    "line_expected": "",
    "size_ok": true,
    "free_ship": false,
    "frete": null,
    "local": "",
    "vendedor": "",
    "condicao": "Novo",
    "frete_gratis": false,
    "marketplace": "mercadolivre",
    "marca": "goodyear",
    "data_coleta": "2025-08-08 16:49:51",
    "preco_original": null,
    "preco_desconto": 249.0,
    "desconto_pct": null,
    "shipping": {}
  },
  {
    "titulo": "Pneu 205 55 16 Goodyear Eagle Sport Usado Meia Vida V",
    "link": "https://www.mercadolivre.com.br/pneu-205-55-16-goodyear-eagle-sport-usado-meia-vida/up/MLBU3171165329",
    "preco": 130.0,
    "query_strict": "",
    "size_norm": "",
    "brand_expected": "",
    "line_expected": "",
    "size_ok": true,
    "free_ship": false,
    "frete": null,
    "local": "",
    "vendedor": "",
    "condicao": "Novo",
    "frete_gratis": false,
    "marketplace": "mercadolivre",
    "marca": "goodyear",
    "data_coleta": "2025-08-08 16:49:53",
    "preco_original": null,
    "preco_desconto": 130.0,
    "desconto_pct": null,
    "shipping": {}
  },
  {
    "titulo": "Pneu 205 55 16 Goodyear Eagle Sport 2 Usado Meia Vida V",
    "link": "https://www.mercadolivre.com.br/pneu-205-55-16-goodyear-eagle-sport-2-usado-meia-vida/up/MLBU3170714207",
    "preco": 190.0,
    "query_strict": "",
    "size_norm": "",
    "brand_expected": "",
    "line_expected": "",
    "size_ok": true,
    "free_ship": false,
    "frete": null,
    "local": "",
    "vendedor": "",
    "condicao": "Novo",
    "frete_gratis": false,
    "marketplace": "mercadolivre",
    "marca": "goodyear",
    "data_coleta": "2025-08-08 16:49:54",
    "preco_original": null,
    "preco_desconto": 190.0,
    "desconto_pct": null,
    "shipping": {}
  },
  {
    "titulo": "Pneu Good Year Eagle Sport2 205/55 R16 C180 A",
    "link": "https://produto.mercadolivre.com.br/MLB-5421147492-pneu-good-year-eagle-sport2-20555-r16-c180-a-_JM?searchVariation=188287595733",
    "preco": 389.99,
    "query_strict": "",
    "size_norm": "",
    "brand_expected": "",
    "line_expected": "",
    "size_ok": true,
    "free_ship": false,
    "frete": null,
    "local": "",
    "vendedor": "",
    "condicao": "Novo",
    "frete_gratis": false,
    "marketplace": "mercadolivre",
    "marca": "",
    "data_coleta": "2025-08-08 16:49:55",
    "preco_original": null,
    "preco_desconto": 389.99,
    "desconto_pct": null,
    "shipping": {}
  },
  {
    "titulo": "Pneu Good Year Eagle Sport 205/55 R16 C180 C",
    "link": "https://produto.mercadolivre.com.br/MLB-5421177618-pneu-good-year-eagle-sport-20555-r16-c180-c-_JM?searchVariation=188287615281",
    "preco": 269.99,
    "query_strict": "",
    "size_norm": "",
    "brand_expected": "",
    "line_expected": "",
    "size_ok": true,
    "free_ship": false,
    "frete": null,
    "local": "",
    "vendedor": "",
    "condicao": "Novo",
    "frete_gratis": false,
    "marketplace": "mercadolivre",
    "marca": "",
    "data_coleta": "2025-08-08 16:49:57",
    "preco_original": null,
    "preco_desconto": 269.99,
    "desconto_pct": null,
    "shipping": {}
  },
  {
    "titulo": "Pneu Goodyear Aro 16 Eagle Sport 2 205/55r16 91v Sl",
    "link": "https://produto.mercadolivre.com.br/MLB-3513728999-pneu-goodyear-aro-16-eagle-sport-2-20555r16-91v-sl-_JM?searchVariation=181209341631",
    "preco": 589.99,
    "query_strict": "",
    "size_norm": "",
    "brand_expected": "",
    "line_expected": "",
    "size_ok": true,
    "free_ship": true,
    "frete": 0.0,
    "local": "",
    "vendedor": "",
    "condicao": "Novo",
    "frete_gratis": true,
    "marketplace": "mercadolivre",
    "marca": "goodyear",
    "data_coleta": "2025-08-08 16:49:58",
    "preco_original": null,
    "preco_desconto": 589.99,
    "desconto_pct": null,
    "shipping": {}
  },
  {
    "titulo": "Pneu Goodyear Aro 16 Eagle Sport 2 205/55r16 91v Sl",
    "link": "https://produto.mercadolivre.com.br/MLB-3513793689-pneu-goodyear-aro-16-eagle-sport-2-20555r16-91v-sl-_JM?searchVariation=181209913359",
    "preco": 565.99,
    "query_strict": "",
    "size_norm": "",
    "brand_expected": "",
    "line_expected": "",
    "size_ok": true,
    "free_ship": true,
    "frete": 0.0,
    "local": "",
    "vendedor": "",
    "condicao": "Novo",
    "frete_gratis": true,
    "marketplace": "mercadolivre",
    "marca": "goodyear",
    "data_coleta": "2025-08-08 16:49:59",
    "preco_original": null,
    "preco_desconto": 565.99,
    "desconto_pct": null,
    "shipping": {}
  }
]