[
  {
    "titulo": "Pneu Dunlop 195/50r16 84v Direzza Dz102 Índice De Velocidade V",
    "link": "https://www.mercadolivre.com.br/pneu-dunlop-19550r16-84v-direzza-dz102-indice-de-velocidade-v/p/MLB29693157",
    "preco": 533.0,
    "brand": "dunlop",
    "model": "direzza",
    "size": "",
    "query_strict": "pneu 195/50R16 Dunlop Direzza",
    "size_norm": "195-50-r16",
    "brand_expected": "dunlop",
    "line_expected": "direzza",
    "size_ok": true,
    "free_ship": true,
    "frete": 0.0,
    "local": "",
    "vendedor": "",
    "condicao": "Novo",
    "frete_gratis": true,
    "marketplace": "mercadolivre",
    "marca": "dunlop",
    "data_coleta": "2025-08-14 18:29:28",
    "preco_original": null,
    "preco_desconto": 533.0,
    "desconto_pct": null,
    "shipping": {}
  },
  {
    "titulo": "Pneu Aro 16 Dunlop 195/50r16 Direzza Dz-102 84v",
    "link": "https://produto.mercadolivre.com.br/MLB-5235291636-pneu-aro-16-dunlop-19550r16-direzza-dz-102-84v-_JM",
    "preco": 606.15,
    "brand": "dunlop",
    "model": "direzza",
    "size": "",
    "query_strict": "pneu 195/50R16 Dunlop Direzza",
    "size_norm": "195-50-r16",
    "brand_expected": "dunlop",
    "line_expected": "direzza",
    "size_ok": true,
    "free_ship": true,
    "frete": 0.0,
    "local": "",
    "vendedor": "",
    "condicao": "Novo",
    "frete_gratis": true,
    "marketplace": "mercadolivre",
    "marca": "dunlop",
    "data_coleta": "2025-08-14 18:29:29",
    "preco_original": null,
    "preco_desconto": 606.15,
    "desconto_pct": null,
    "shipping": {}
  },
  {
    "titulo": "Pneu Dunlop 195/50r16 84v Dz102",
    "link": "https://produto.mercadolivre.com.br/MLB-3258754231-pneu-dunlop-19550r16-84v-dz102-_JM",
    "preco": 723.9,
    "brand": "dunlop",
    "model": "direzza",
    "size": "",
    "query_strict": "pneu 195/50R16 Dunlop Direzza",
    "size_norm": "195-50-r16",
    "brand_expected": "dunlop",
    "line_expected": "direzza",
    "size_ok": true,
    "free_ship": true,
    "frete": 0.0,
    "local": "",
    "vendedor": "",
    "condicao": "Novo",
    "frete_gratis": true,
    "marketplace": "mercadolivre",
    "marca": "dunlop",
    "data_coleta": "2025-08-14 18:29:31",
    "preco_original": null,
    "preco_desconto": 723.9,
    "desconto_pct": null,
    "shipping": {}
  },
  {
    "titulo": "Pneu Dunlop 195/50r16 Direzza Dz-102 84v",
    "link": "https://produto.mercadolivre.com.br/MLB-3940991761-pneu-dunlop-19550r16-direzza-dz-102-84v-_JM",
    "preco": 606.15,
    "brand": "dunlop",
    "model": "direzza",
    "size": "",
    "query_strict": "pneu 195/50R16 Dunlop Direzza",
    "size_norm": "195-50-r16",
    "brand_expected": "dunlop",
    "line_expected": "direzza",
    "size_ok": true,
    "free_ship": true,
    "frete": 0.0,
    "local": "",
    "vendedor": "",
    "condicao": "Novo",
    "frete_gratis": true,
    "marketplace": "mercadolivre",
    "marca": "dunlop",
    "data_coleta": "2025-08-14 18:29:33",
    "preco_original": null,
    "preco_desconto": 606.15,
    "desconto_pct": null,
    "shipping": {}
  },
  {
    "titulo": "Pneu 195/50 R16 Dunlop Direzza Dz102 84v",
    "link": "https://produto.mercadolivre.com.br/MLB-5366002490-pneu-19550-r16-dunlop-direzza-dz102-84v-_JM?searchVariation=187678838427",
    "preco": 613.21,
    "brand": "dunlop",
    "model": "direzza",
    "size": "",
    "query_strict": "pneu 195/50R16 Dunlop Direzza",
    "size_norm": "195-50-r16",
    "brand_expected": "dunlop",
    "line_expected": "direzza",
    "size_ok": true,
    "free_ship": true,
    "frete": 0.0,
    "local": "",
    "vendedor": "",
    "condicao": "Novo",
    "frete_gratis": true,
    "marketplace": "mercadolivre",
    "marca": "dunlop",
    "data_coleta": "2025-08-14 18:29:35",
    "preco_original": null,
    "preco_desconto": 613.21,
    "desconto_pct": null,
    "shipping": {}
  },
  {
    "titulo": "Pneu Dunlop Aro 16 195/50r16 Direzza Dz-102 84v",
    "link": "https://produto.mercadolivre.com.br/MLB-5249490680-pneu-dunlop-aro-16-19550r16-direzza-dz-102-84v-_JM",
    "preco": 651.66,
    "brand": "dunlop",
    "model": "direzza",
    "size": "",
    "query_strict": "pneu 195/50R16 Dunlop Direzza",
    "size_norm": "195-50-r16",
    "brand_expected": "dunlop",
    "line_expected": "direzza",
    "size_ok": true,
    "free_ship": true,
    "frete": 0.0,
    "local": "",
    "vendedor": "",
    "condicao": "Novo",
    "frete_gratis": true,
    "marketplace": "mercadolivre",
    "marca": "dunlop",
    "data_coleta": "2025-08-14 18:29:37",
    "preco_original": null,
    "preco_desconto": 651.66,
    "desconto_pct": null,
    "shipping": {}
  },
  {
    "titulo": "Pneu Dunlop 195/50r16 84v Dz102",
    "link": "https://produto.mercadolivre.com.br/MLB-3312675948-pneu-dunlop-19550r16-84v-dz102-_JM",
    "preco": 670.9,
    "brand": "dunlop",
    "model": "direzza",
    "size": "",
    "query_strict": "pneu 195/50R16 Dunlop Direzza",
    "size_norm": "195-50-r16",
    "brand_expected": "dunlop",
    "line_expected": "direzza",
    "size_ok": true,
    "free_ship": true,
    "frete": 0.0,
    "local": "",
    "vendedor": "",
    "condicao": "Novo",
    "frete_gratis": true,
    "marketplace": "mercadolivre",
    "marca": "dunlop",
    "data_coleta": "2025-08-14 18:29:38",
    "preco_original": null,
    "preco_desconto": 670.9,
    "desconto_pct": null,
    "shipping": {}
  },
  {
    "titulo": "Pneu Dunlop Aro 16 195/50r16 Direzza Dz-102 84v",
    "link": "https://produto.mercadolivre.com.br/MLB-3800617329-pneu-dunlop-aro-16-19550r16-direzza-dz-102-84v-_JM",
    "preco": 749.91,
    "brand": "dunlop",
    "model": "direzza",
    "size": "",
    "query_strict": "pneu 195/50R16 Dunlop Direzza",
    "size_norm": "195-50-r16",
    "brand_expected": "dunlop",
    "line_expected": "direzza",
    "size_ok": true,
    "free_ship": true,
    "frete": 0.0,
    "local": "",
    "vendedor": "",
    "condicao": "Novo",
    "frete_gratis": true,
    "marketplace": "mercadolivre",
    "marca": "dunlop",
    "data_coleta": "2025-08-14 18:29:39",
    "preco_original": null,
    "preco_desconto": 749.91,
    "desconto_pct": null,
    "shipping": {}
  },
  {
    "titulo": "Pneu Dunlop Aro 16 195/50r16 Direzza Dz-102",
    "link": "https://produto.mercadolivre.com.br/MLB-4964497624-pneu-dunlop-aro-16-19550r16-direzza-dz-102-_JM",
    "preco": 749.91,
    "brand": "dunlop",
    "model": "direzza",
    "size": "",
    "query_strict": "pneu 195/50R16 Dunlop Direzza",
    "size_norm": "195-50-r16",
    "brand_expected": "dunlop",
    "line_expected": "direzza",
    "size_ok": true,
    "free_ship": true,
    "frete": 0.0,
    "local": "",
    "vendedor": "",
    "condicao": "Novo",
    "frete_gratis": true,
    "marketplace": "mercadolivre",
    "marca": "dunlop",
    "data_coleta": "2025-08-14 18:29:41",
    "preco_original": null,
    "preco_desconto": 749.91,
    "desconto_pct": null,
    "shipping": {}
  },
  {
    "titulo": "Pneu Dunlop 195/50r16 Direzza Dz-102 84v",
    "link": "https://produto.mercadolivre.com.br/MLB-3940958841-pneu-dunlop-19550r16-direzza-dz-102-84v-_JM",
    "preco": 555.44,
    "brand": "dunlop",
    "model": "direzza",
    "size": "",
    "query_strict": "pneu 195/50R16 Dunlop Direzza",
    "size_norm": "195-50-r16",
    "brand_expected": "dunlop",
    "line_expected": "direzza",
    "size_ok": true,
    "free_ship": true,
    "frete": 0.0,
    "local": "",
    "vendedor": "",
    "condicao": "Novo",
    "frete_gratis": true,
    "marketplace": "mercadolivre",
    "marca": "dunlop",
    "data_coleta": "2025-08-14 18:29:43",
    "preco_original": null,
    "preco_desconto": 555.44,
    "desconto_pct": null,
    "shipping": {}
  },
  {
    "titulo": "Pneu Dunlop Aro 16 195/50r16 Direzza Dz-102 84v",
    "link": "https://produto.mercadolivre.com.br/MLB-4964459648-pneu-dunlop-aro-16-19550r16-direzza-dz-102-84v-_JM",
    "preco": 697.54,
    "brand": "dunlop",
    "model": "direzza",
    "size": "",
    "query_strict": "pneu 195/50R16 Dunlop Direzza",
    "size_norm": "195-50-r16",
    "brand_expected": "dunlop",
    "line_expected": "direzza",
    "size_ok": true,
    "free_ship": true,
    "frete": 0.0,
    "local": "",
    "vendedor": "",
    "condicao": "Novo",
    "frete_gratis": true,
    "marketplace": "mercadolivre",
    "marca": "dunlop",
    "data_coleta": "2025-08-14 18:29:45",
    "preco_original": null,
    "preco_desconto": 697.54,
    "desconto_pct": null,
    "shipping": {}
  },
  {
    "titulo": "Pneu Dunlop Aro 16 195/50r16 Direzza Dz-102",
    "link": "https://produto.mercadolivre.com.br/MLB-4964572538-pneu-dunlop-aro-16-19550r16-direzza-dz-102-_JM",
    "preco": 697.54,
    "brand": "dunlop",
    "model": "direzza",
    "size": "",
    "query_strict": "pneu 195/50R16 Dunlop Direzza",
    "size_norm": "195-50-r16",
    "brand_expected": "dunlop",
    "line_expected": "direzza",
    "size_ok": true,
    "free_ship": true,
    "frete": 0.0,
    "local": "",
    "vendedor": "",
    "condicao": "Novo",
    "frete_gratis": true,
    "marketplace": "mercadolivre",
    "marca": "dunlop",
    "data_coleta": "2025-08-14 18:29:46",
    "preco_original": null,
    "preco_desconto": 697.54,
    "desconto_pct": null,
    "shipping": {}
  },
  {
    "titulo": "Pneu Dunlop Aro 16 195/50r16 Direzza Dz-102 84v",
    "link": "https://produto.mercadolivre.com.br/MLB-5249491242-pneu-dunlop-aro-16-19550r16-direzza-dz-102-84v-_JM",
    "preco": 653.31,
    "brand": "dunlop",
    "model": "direzza",
    "size": "",
    "query_strict": "pneu 195/50R16 Dunlop Direzza",
    "size_norm": "195-50-r16",
    "brand_expected": "dunlop",
    "line_expected": "direzza",
    "size_ok": true,
    "free_ship": true,
    "frete": 0.0,
    "local": "",
    "vendedor": "",
    "condicao": "Novo",
    "frete_gratis": true,
    "marketplace": "mercadolivre",
    "marca": "dunlop",
    "data_coleta": "2025-08-14 18:29:47",
    "preco_original": null,
    "preco_desconto": 653.31,
    "desconto_pct": null,
    "shipping": {}
  },
  {
    "titulo": "Pneu Dunlop Aro 16 195/50r16 Direzza Dz-102 84v",
    "link": "https://produto.mercadolivre.com.br/MLB-5249582148-pneu-dunlop-aro-16-19550r16-direzza-dz-102-84v-_JM",
    "preco": 653.74,
    "brand": "dunlop",
    "model": "direzza",
    "size": "",
    "query_strict": "pneu 195/50R16 Dunlop Direzza",
    "size_norm": "195-50-r16",
    "brand_expected": "dunlop",
    "line_expected": "direzza",
    "size_ok": true,
    "free_ship": true,
    "frete": 0.0,
    "local": "",
    "vendedor": "",
    "condicao": "Novo",
    "frete_gratis": true,
    "marketplace": "mercadolivre",
    "marca": "dunlop",
    "data_coleta": "2025-08-14 18:29:49",
    "preco_original": null,
    "preco_desconto": 653.74,
    "desconto_pct": null,
    "shipping": {}
  },
  {
    "titulo": "Pneu Dunlop Aro 16 195/50r16 Direzza Dz-102 84v",
    "link": "https://www.mercadolivre.com.br/pneu-dunlop-aro-16-19550r16-direzza-dz-102-84v/p/MLB45405354",
    "preco": 699.0,
    "brand": "dunlop",
    "model": "direzza",
    "size": "",
    "query_strict": "pneu 195/50R16 Dunlop Direzza",
    "size_norm": "195-50-r16",
    "brand_expected": "dunlop",
    "line_expected": "direzza",
    "size_ok": true,
    "free_ship": true,
    "frete": 0.0,
    "local": "",
    "vendedor": "",
    "condicao": "Novo",
    "frete_gratis": true,
    "marketplace": "mercadolivre",
    "marca": "dunlop",
    "data_coleta": "2025-08-14 18:29:51",
    "preco_original": null,
    "preco_desconto": 699.0,
    "desconto_pct": null,
    "shipping": {}
  },
  {
    "titulo": "Pneu Dunlop Aro 16 195/50r16 Direzza Dz-102 84v",
    "link": "https://produto.mercadolivre.com.br/MLB-5037295352-pneu-dunlop-aro-16-19550r16-direzza-dz-102-84v-_JM",
    "preco": 613.84,
    "brand": "dunlop",
    "model": "direzza",
    "size": "",
    "query_strict": "pneu 195/50R16 Dunlop Direzza",
    "size_norm": "195-50-r16",
    "brand_expected": "dunlop",
    "line_expected": "direzza",
    "size_ok": true,
    "free_ship": true,
    "frete": 0.0,
    "local": "",
    "vendedor": "",
    "condicao": "Novo",
    "frete_gratis": true,
    "marketplace": "mercadolivre",
    "marca": "dunlop",
    "data_coleta": "2025-08-14 18:29:52",
    "preco_original": null,
    "preco_desconto": 613.84,
    "desconto_pct": null,
    "shipping": {}
  },
  {
    "titulo": "Pneu Aro 16 Dunlop 195/50r16 Direzza Dz-102 84v",
    "link": "https://produto.mercadolivre.com.br/MLB-5235291612-pneu-aro-16-dunlop-19550r16-direzza-dz-102-84v-_JM",
    "preco": 555.44,
    "brand": "dunlop",
    "model": "direzza",
    "size": "",
    "query_strict": "pneu 195/50R16 Dunlop Direzza",
    "size_norm": "195-50-r16",
    "brand_expected": "dunlop",
    "line_expected": "direzza",
    "size_ok": true,
    "free_ship": true,
    "frete": 0.0,
    "local": "",
    "vendedor": "",
    "condicao": "Novo",
    "frete_gratis": true,
    "marketplace": "mercadolivre",
    "marca": "dunlop",
    "data_coleta": "2025-08-14 18:29:54",
    "preco_original": null,
    "preco_desconto": 555.44,
    "desconto_pct": null,
    "shipping": {}
  },
  {
    "titulo": "Pneu Dunlop Direzza 195/50r16 84v Aro 16 Alta Performance V",
    "link": "https://www.mercadolivre.com.br/pneu-dunlop-direzza-19550r16-84v-aro-16-alta-performance/up/MLBU3358601327",
    "preco": 793.92,
    "brand": "dunlop",
    "model": "direzza",
    "size": "",
    "query_strict": "pneu 195/50R16 Dunlop Direzza",
    "size_norm": "195-50-r16",
    "brand_expected": "dunlop",
    "line_expected": "direzza",
    "size_ok": true,
    "free_ship": true,
    "frete": 0.0,
    "local": "",
    "vendedor": "",
    "condicao": "Novo",
    "frete_gratis": true,
    "marketplace": "mercadolivre",
    "marca": "dunlop",
    "data_coleta": "2025-08-14 18:29:55",
    "preco_original": null,
    "preco_desconto": 793.92,
    "desconto_pct": null,
    "shipping": {}
  },
  {
    "titulo": "Pneu Dunlop Aro 16 195/50r16 Direzza Dz-102 84v V",
    "link": "https://www.mercadolivre.com.br/pneu-dunlop-aro-16-19550r16-direzza-dz102-84v/up/MLBU1169667226",
    "preco": 659.69,
    "brand": "dunlop",
    "model": "direzza",
    "size": "",
    "query_strict": "pneu 195/50R16 Dunlop Direzza",
    "size_norm": "195-50-r16",
    "brand_expected": "dunlop",
    "line_expected": "direzza",
    "size_ok": true,
    "free_ship": true,
    "frete": 0.0,
    "local": "",
    "vendedor": "",
    "condicao": "Novo",
    "frete_gratis": true,
    "marketplace": "mercadolivre",
    "marca": "dunlop",
    "data_coleta": "2025-08-14 18:29:57",
    "preco_original": null,
    "preco_desconto": 659.69,
    "desconto_pct": null,
    "shipping": {}
  },
  {
    "titulo": "Pneu 195/50r16 Direzza Dz102 Dunlop 84v Aro 16 V",
    "link": "https://www.mercadolivre.com.br/pneu-19550r16-direzza-dz102-dunlop-84v-aro-16/up/MLBU3364640014",
    "preco": 721.75,
    "brand": "dunlop",
    "model": "direzza",
    "size": "",
    "query_strict": "pneu 195/50R16 Dunlop Direzza",
    "size_norm": "195-50-r16",
    "brand_expected": "dunlop",
    "line_expected": "direzza",
    "size_ok": true,
    "free_ship": true,
    "frete": 0.0,
    "local": "",
    "vendedor": "",
    "condicao": "Novo",
    "frete_gratis": true,
    "marketplace": "mercadolivre",
    "marca": "dunlop",
    "data_coleta": "2025-08-14 18:29:58",
    "preco_original": null,
    "preco_desconto": 721.75,
    "desconto_pct": null,
    "shipping": {}
  },
  {
    "titulo": "Pneu Aro 16 195/50r16 Dunlop Direzza Dz102 84v",
    "link": "https://www.mercadolivre.com.br/pneu-aro-16-19550r16-dunlop-direzza-dz102-84v/up/MLBU3044244820",
    "preco": 593.35,
    "brand": "dunlop",
    "model": "direzza",
    "size": "",
    "query_strict": "pneu 195/50R16 Dunlop Direzza",
    "size_norm": "195-50-r16",
    "brand_expected": "dunlop",
    "line_expected": "direzza",
    "size_ok": true,
    "free_ship": true,
    "frete": 0.0,
    "local": "",
    "vendedor": "",
    "condicao": "Novo",
    "frete_gratis": true,
    "marketplace": "mercadolivre",
    "marca": "dunlop",
    "data_coleta": "2025-08-14 18:30:32",
    "preco_original": null,
    "preco_desconto": 593.35,
    "desconto_pct": null,
    "shipping": {}
  },
  {
    "titulo": "Pneu Dunlop Aro 16 195/50r16 Direzza Dz-102 84v",
    "link": "https://produto.mercadolivre.com.br/MLB-5249459352-pneu-dunlop-aro-16-19550r16-direzza-dz-102-84v-_JM",
    "preco": 737.73,
    "brand": "dunlop",
    "model": "direzza",
    "size": "",
    "query_strict": "pneu 195/50R16 Dunlop Direzza",
    "size_norm": "195-50-r16",
    "brand_expected": "dunlop",
    "line_expected": "direzza",
    "size_ok": true,
    "free_ship": true,
    "frete": 0.0,
    "local": "",
    "vendedor": "",
    "condicao": "Novo",
    "frete_gratis": true,
    "marketplace": "mercadolivre",
    "marca": "dunlop",
    "data_coleta": "2025-08-14 18:30:33",
    "preco_original": null,
    "preco_desconto": 737.73,
    "desconto_pct": null,
    "shipping": {}
  },
  {
    "titulo": "Pneu 195/50r16 Dunlop Direzza Dz102 84v",
    "link": "https://www.mercadolivre.com.br/pneu-19550r16-dunlop-direzza-dz102-84v/up/MLBU3044247218",
    "preco": 633.34,
    "brand": "dunlop",
    "model": "direzza",
    "size": "",
    "query_strict": "pneu 195/50R16 Dunlop Direzza",
    "size_norm": "195-50-r16",
    "brand_expected": "dunlop",
    "line_expected": "direzza",
    "size_ok": true,
    "free_ship": true,
    "frete": 0.0,
    "local": "",
    "vendedor": "",
    "condicao": "Novo",
    "frete_gratis": true,
    "marketplace": "mercadolivre",
    "marca": "dunlop",
    "data_coleta": "2025-08-14 18:30:35",
    "preco_original": null,
    "preco_desconto": 633.34,
    "desconto_pct": null,
    "shipping": {}
  },
  {
    "titulo": "Pneu Dunlop  Direzza Dz102 V 195/50r16 84v V",
    "link": "https://www.mercadolivre.com.br/pneu-dunlop--direzza-dz102-v-19550r16-84v/up/MLBU3319185596",
    "preco": 723.26,
    "brand": "dunlop",
    "model": "direzza",
    "size": "",
    "query_strict": "pneu 195/50R16 Dunlop Direzza",
    "size_norm": "195-50-r16",
    "brand_expected": "dunlop",
    "line_expected": "direzza",
    "size_ok": true,
    "free_ship": true,
    "frete": 0.0,
    "local": "",
    "vendedor": "",
    "condicao": "Novo",
    "frete_gratis": true,
    "marketplace": "mercadolivre",
    "marca": "dunlop",
    "data_coleta": "2025-08-14 18:30:36",
    "preco_original": null,
    "preco_desconto": 723.26,
    "desconto_pct": null,
    "shipping": {}
  },
  {
    "titulo": "Pneu Dunlop 195/50r16 84v Direzza Dz102 V",
    "link": "https://www.mercadolivre.com.br/pneu-dunlop-19550r16-84v-direzza-dz102/up/MLBU3305557743",
    "preco": 676.6,
    "brand": "dunlop",
    "model": "direzza",
    "size": "",
    "query_strict": "pneu 195/50R16 Dunlop Direzza",
    "size_norm": "195-50-r16",
    "brand_expected": "dunlop",
    "line_expected": "direzza",
    "size_ok": true,
    "free_ship": true,
    "frete": 0.0,
    "local": "",
    "vendedor": "",
    "condicao": "Novo",
    "frete_gratis": true,
    "marketplace": "mercadolivre",
    "marca": "dunlop",
    "data_coleta": "2025-08-14 18:30:38",
    "preco_original": null,
    "preco_desconto": 676.6,
    "desconto_pct": null,
    "shipping": {}
  },
  {
    "titulo": "Pneu 195/50 R16 Dunlop Direzza Dz102 P/ New Fiesta Gol G5",
    "link": "https://produto.mercadolivre.com.br/MLB-959172946-pneu-19550-r16-dunlop-direzza-dz102-p-new-fiesta-gol-g5-_JM",
    "preco": 1122.0,
    "brand": "dunlop",
    "model": "direzza",
    "size": "",
    "query_strict": "pneu 195/50R16 Dunlop Direzza",
    "size_norm": "195-50-r16",
    "brand_expected": "dunlop",
    "line_expected": "direzza",
    "size_ok": true,
    "free_ship": true,
    "frete": 0.0,
    "local": "",
    "vendedor": "",
    "condicao": "Novo",
    "frete_gratis": true,
    "marketplace": "mercadolivre",
    "marca": "dunlop",
    "data_coleta": "2025-08-14 18:30:40",
    "preco_original": null,
    "preco_desconto": 1122.0,
    "desconto_pct": null,
    "shipping": {}
  },
  {
    "titulo": "Pneu Dunlop Aro 16 195/50r16 Direzza Dz-102 84v V",
    "link": "https://www.mercadolivre.com.br/pneu-dunlop-aro-16-19550r16-direzza-dz102-84v/up/MLBU1760783995",
    "preco": 827.85,
    "brand": "dunlop",
    "model": "direzza",
    "size": "",
    "query_strict": "pneu 195/50R16 Dunlop Direzza",
    "size_norm": "195-50-r16",
    "brand_expected": "dunlop",
    "line_expected": "direzza",
    "size_ok": true,
    "free_ship": true,
    "frete": 0.0,
    "local": "",
    "vendedor": "",
    "condicao": "Novo",
    "frete_gratis": true,
    "marketplace": "mercadolivre",
    "marca": "dunlop",
    "data_coleta": "2025-08-14 18:30:41",
    "preco_original": null,
    "preco_desconto": 827.85,
    "desconto_pct": null,
    "shipping": {}
  },
  {
    "titulo": "Pneu Dunlop Aro 16 195/50r16 Direzza Dz-102 84v V",
    "link": "https://www.mercadolivre.com.br/pneu-dunlop-aro-16-19550r16-direzza-dz102-84v/up/MLBU681389077",
    "preco": 579.0,
    "brand": "dunlop",
    "model": "direzza",
    "size": "",
    "query_strict": "pneu 195/50R16 Dunlop Direzza",
    "size_norm": "195-50-r16",
    "brand_expected": "dunlop",
    "line_expected": "direzza",
    "size_ok": true,
    "free_ship": true,
    "frete": 0.0,
    "local": "",
    "vendedor": "",
    "condicao": "Novo",
    "frete_gratis": true,
    "marketplace": "mercadolivre",
    "marca": "dunlop",
    "data_coleta": "2025-08-14 18:30:43",
    "preco_original": null,
    "preco_desconto": 579.0,
    "desconto_pct": null,
    "shipping": {}
  },
  {
    "titulo": "Pneu Dunlop Aro 16 195/50r16 Direzza Dz-102 84v",
    "link": "https://www.mercadolivre.com.br/pneu-dunlop-aro-16-19550r16-direzza-dz102-84v/up/MLBU1748159194",
    "preco": 781.85,
    "brand": "dunlop",
    "model": "direzza",
    "size": "",
    "query_strict": "pneu 195/50R16 Dunlop Direzza",
    "size_norm": "195-50-r16",
    "brand_expected": "dunlop",
    "line_expected": "direzza",
    "size_ok": true,
    "free_ship": true,
    "frete": 0.0,
    "local": "",
    "vendedor": "",
    "condicao": "Novo",
    "frete_gratis": true,
    "marketplace": "mercadolivre",
    "marca": "dunlop",
    "data_coleta": "2025-08-14 18:30:44",
    "preco_original": null,
    "preco_desconto": 781.85,
    "desconto_pct": null,
    "shipping": {}
  },
  {
    "titulo": "Pneu Dunlop Aro 16 195/50r16 Direzza Dz-102 84v V",
    "link": "https://www.mercadolivre.com.br/pneu-dunlop-aro-16-19550r16-direzza-dz102-84v/up/MLBU3246912725",
    "preco": 720.54,
    "brand": "dunlop",
    "model": "direzza",
    "size": "",
    "query_strict": "pneu 195/50R16 Dunlop Direzza",
    "size_norm": "195-50-r16",
    "brand_expected": "dunlop",
    "line_expected": "direzza",
    "size_ok": true,
    "free_ship": true,
    "frete": 0.0,
    "local": "",
    "vendedor": "",
    "condicao": "Novo",
    "frete_gratis": true,
    "marketplace": "mercadolivre",
    "marca": "dunlop",
    "data_coleta": "2025-08-14 18:30:46",
    "preco_original": null,
    "preco_desconto": 720.54,
    "desconto_pct": null,
    "shipping": {}
  },
  {
    "titulo": "Pneu Dunlop Aro 16 195/50r16 Direzza Dz-102 84v",
    "link": "https://www.mercadolivre.com.br/pneu-dunlop-aro-16-19550r16-direzza-dz102-84v/up/MLBU2942545360",
    "preco": 670.25,
    "brand": "dunlop",
    "model": "direzza",
    "size": "",
    "query_strict": "pneu 195/50R16 Dunlop Direzza",
    "size_norm": "195-50-r16",
    "brand_expected": "dunlop",
    "line_expected": "direzza",
    "size_ok": true,
    "free_ship": true,
    "frete": 0.0,
    "local": "",
    "vendedor": "",
    "condicao": "Novo",
    "frete_gratis": true,
    "marketplace": "mercadolivre",
    "marca": "dunlop",
    "data_coleta": "2025-08-14 18:30:47",
    "preco_original": null,
    "preco_desconto": 670.25,
    "desconto_pct": null,
    "shipping": {}
  },
  {
    "titulo": "Pneu Dunlop Aro 16 195/50r16 Direzza Dz-102 84v",
    "link": "https://produto.mercadolivre.com.br/MLB-5249476372-pneu-dunlop-aro-16-19550r16-direzza-dz-102-84v-_JM",
    "preco": 657.29,
    "brand": "dunlop",
    "model": "direzza",
    "size": "",
    "query_strict": "pneu 195/50R16 Dunlop Direzza",
    "size_norm": "195-50-r16",
    "brand_expected": "dunlop",
    "line_expected": "direzza",
    "size_ok": true,
    "free_ship": true,
    "frete": 0.0,
    "local": "",
    "vendedor": "",
    "condicao": "Novo",
    "frete_gratis": true,
    "marketplace": "mercadolivre",
    "marca": "dunlop",
    "data_coleta": "2025-08-14 18:30:49",
    "preco_original": null,
    "preco_desconto": 657.29,
    "desconto_pct": null,
    "shipping": {}
  },
  {
    "titulo": "Pneu 195/50 R16 Dunlop Direzza Dz102 84v",
    "link": "https://produto.mercadolivre.com.br/MLB-4043532369-pneu-19550-r16-dunlop-direzza-dz102-84v-_JM?searchVariation=187678862257",
    "preco": 597.08,
    "brand": "dunlop",
    "model": "direzza",
    "size": "",
    "query_strict": "pneu 195/50R16 Dunlop Direzza",
    "size_norm": "195-50-r16",
    "brand_expected": "dunlop",
    "line_expected": "direzza",
    "size_ok": true,
    "free_ship": true,
    "frete": 0.0,
    "local": "",
    "vendedor": "",
    "condicao": "Novo",
    "frete_gratis": true,
    "marketplace": "mercadolivre",
    "marca": "dunlop",
    "data_coleta": "2025-08-14 18:30:50",
    "preco_original": null,
    "preco_desconto": 597.08,
    "desconto_pct": null,
    "shipping": {}
  },
  {
    "titulo": "Pneu Dunlop Aro 16 195/50r16 Direzza Dz-102 84v",
    "link": "https://produto.mercadolivre.com.br/MLB-5249554854-pneu-dunlop-aro-16-19550r16-direzza-dz-102-84v-_JM",
    "preco": 658.01,
    "brand": "dunlop",
    "model": "direzza",
    "size": "",
    "query_strict": "pneu 195/50R16 Dunlop Direzza",
    "size_norm": "195-50-r16",
    "brand_expected": "dunlop",
    "line_expected": "direzza",
    "size_ok": true,
    "free_ship": true,
    "frete": 0.0,
    "local": "",
    "vendedor": "",
    "condicao": "Novo",
    "frete_gratis": true,
    "marketplace": "mercadolivre",
    "marca": "dunlop",
    "data_coleta": "2025-08-14 18:30:52",
    "preco_original": null,
    "preco_desconto": 658.01,
    "desconto_pct": null,
    "shipping": {}
  },
  {
    "titulo": "Pneu Dunlop Aro 16 195/50r16 Direzza Dz-102 84v",
    "link": "https://produto.mercadolivre.com.br/MLB-3520469979-pneu-dunlop-aro-16-19550r16-direzza-dz-102-84v-_JM",
    "preco": 613.84,
    "brand": "dunlop",
    "model": "direzza",
    "size": "",
    "query_strict": "pneu 195/50R16 Dunlop Direzza",
    "size_norm": "195-50-r16",
    "brand_expected": "dunlop",
    "line_expected": "direzza",
    "size_ok": true,
    "free_ship": true,
    "frete": 0.0,
    "local": "",
    "vendedor": "",
    "condicao": "Novo",
    "frete_gratis": true,
    "marketplace": "mercadolivre",
    "marca": "dunlop",
    "data_coleta": "2025-08-14 18:30:54",
    "preco_original": null,
    "preco_desconto": 613.84,
    "desconto_pct": null,
    "shipping": {}
  },
  {
    "titulo": "Pneu Dunlop Aro 16 195/50r16 Direzza Dz-102 84v",
    "link": "https://www.mercadolivre.com.br/pneu-dunlop-aro-16-19550r16-direzza-dz-102-84v/p/MLB46493693",
    "preco": 646.88,
    "brand": "dunlop",
    "model": "direzza",
    "size": "",
    "query_strict": "pneu 195/50R16 Dunlop Direzza",
    "size_norm": "195-50-r16",
    "brand_expected": "dunlop",
    "line_expected": "direzza",
    "size_ok": true,
    "free_ship": true,
    "frete": 0.0,
    "local": "",
    "vendedor": "",
    "condicao": "Novo",
    "frete_gratis": true,
    "marketplace": "mercadolivre",
    "marca": "dunlop",
    "data_coleta": "2025-08-14 18:30:56",
    "preco_original": null,
    "preco_desconto": 646.88,
    "desconto_pct": null,
    "shipping": {}
  },
  {
    "titulo": "Pneu 195 50 R16 Dunlop",
    "link": "https://produto.mercadolivre.com.br/MLB-3934635483-pneu-195-50-r16-dunlop-_JM",
    "preco": 349.0,
    "brand": "dunlop",
    "model": "direzza",
    "size": "",
    "query_strict": "pneu 195/50R16 Dunlop Direzza",
    "size_norm": "195-50-r16",
    "brand_expected": "dunlop",
    "line_expected": "direzza",
    "size_ok": true,
    "free_ship": false,
    "frete": null,
    "local": "",
    "vendedor": "",
    "condicao": "Novo",
    "frete_gratis": false,
    "marketplace": "mercadolivre",
    "marca": "dunlop",
    "data_coleta": "2025-08-14 18:30:57",
    "preco_original": null,
    "preco_desconto": 349.0,
    "desconto_pct": null,
    "shipping": {}
  },
  {
    "titulo": "Pneu Dunlop Aro 16 195/50r16 Direzza Dz-102 84v",
    "link": "https://produto.mercadolivre.com.br/MLB-4195173312-pneu-dunlop-aro-16-19550r16-direzza-dz-102-84v-_JM",
    "preco": 653.26,
    "brand": "dunlop",
    "model": "direzza",
    "size": "",
    "query_strict": "pneu 195/50R16 Dunlop Direzza",
    "size_norm": "195-50-r16",
    "brand_expected": "dunlop",
    "line_expected": "direzza",
    "size_ok": true,
    "free_ship": true,
    "frete": 0.0,
    "local": "",
    "vendedor": "",
    "condicao": "Novo",
    "frete_gratis": true,
    "marketplace": "mercadolivre",
    "marca": "dunlop",
    "data_coleta": "2025-08-14 18:30:58",
    "preco_original": null,
    "preco_desconto": 653.26,
    "desconto_pct": null,
    "shipping": {}
  }
]