[
  {
    "titulo": "Pneu Aro 15 195/60R15 88V Energy XM2 Plus Michelin",
    "preco": 580.61,
    "link": "https://www.magazineluiza.com.br/pneu-aro-15-195-60r15-88v-energy-xm2-plus-michelin/p/cb64ff955b/au/pine/",
    "data_coleta": "2025-08-11 19:51:59",
    "medida": "195/60R15",
    "marca": "michelin",
    "modelo": "energy xm2",
    "preco_original": 68307975.9,
    "promocao": true,
    "imagem": "https://a-static.mlcdn.com.br/280x210/pneu-aro-15-195-60r15-88v-energy-xm2-plus-michelin/pneubaratocombr/19248/9d22b5d9298a67b175cde9811ab65975.jpeg",
    "marketplace": "magazineluiza",
    "categoria": "",
    "disponivel": true,
    "avaliacoes": 0,
    "nota_media": 0.0,
    "vendedor": "Pneu Barato",
    "frete_gratis": false,
    "parcelamento": "",
    "descricao": "",
    "frete": null
  },
  {
    "titulo": "Pneu Michelin Aro 15 Energy XM2+ 195/60R15 88V",
    "preco": 596.39,
    "link": "https://www.magazineluiza.com.br/pneu-michelin-aro-15-energy-xm2-195-60r15-88v/p/ffehj020k9/au/aupa/",
    "data_coleta": "2025-08-11 19:52:06",
    "medida": "195/60R15",
    "marca": "michelin",
    "modelo": "energy xm2",
    "preco_original": 720.53,
    "promocao": true,
    "imagem": "https://a-static.mlcdn.com.br/280x210/pneu-michelin-aro-15-energy-xm2-195-60r15-88v/pneustore/10110158/74026b318f4c5eb6f3ff8b71ea1fb723.jpeg",
    "marketplace": "magazineluiza",
    "categoria": "",
    "disponivel": true,
    "avaliacoes": 88,
    "nota_media": 8.0,
    "vendedor": "PneuStore",
    "frete_gratis": false,
    "parcelamento": "",
    "descricao": "",
    "frete": null
  },
  {
    "titulo": "Pneu Aro 15 Michelin 195/60 R15 88V TL ENERGY XM2+",
    "preco": 681.35,
    "link": "https://www.magazineluiza.com.br/pneu-aro-15-michelin-195-60-r15-88v-tl-energy-xm2/p/jkkda58kf6/au/aupa/",
    "data_coleta": "2025-08-11 19:52:17",
    "medida": "195/60R15",
    "marca": "michelin",
    "modelo": "energy xm2",
    "preco_original": 745.37,
    "promocao": true,
    "imagem": "https://a-static.mlcdn.com.br/280x210/pneu-aro-15-michelin-195-60-r15-88v-tl-energy-xm2/pneugreen/199/aadef8c00b32a122349a64a0b814339d.jpeg",
    "marketplace": "magazineluiza",
    "categoria": "",
    "disponivel": true,
    "avaliacoes": 88,
    "nota_media": 8.0,
    "vendedor": "Pneugreen",
    "frete_gratis": false,
    "parcelamento": "",
    "descricao": "",
    "frete": null
  },
  {
    "titulo": "Pneu Michelin Aro 15 195/60R15 Energy XM2 88V",
    "preco": 892.15,
    "link": "https://www.magazineluiza.com.br/pneu-michelin-aro-15-195-60r15-energy-xm2-88v/p/he2k2dj23b/au/aupa/",
    "data_coleta": "2025-08-11 19:52:26",
    "medida": "195/60R15",
    "marca": "michelin",
    "modelo": "energy xm2",
    "preco_original": 939111278.26,
    "promocao": true,
    "imagem": "https://a-static.mlcdn.com.br/280x210/pneu-michelin-aro-15-195-60r15-energy-xm2-88v/webpneus/37008/4c57801c154581450131810e95ed3cf3.jpeg",
    "marketplace": "magazineluiza",
    "categoria": "",
    "disponivel": true,
    "avaliacoes": 88,
    "nota_media": 8.0,
    "vendedor": "Web Pneus",
    "frete_gratis": false,
    "parcelamento": "",
    "descricao": "",
    "frete": null
  },
  {
    "titulo": "Pneu Aro 15 195/60R15 88V Energy XM2 Plus Michelin",
    "preco": 580.61,
    "link": "https://www.magazineluiza.com.br/pneu-aro-15-195-60r15-88v-energy-xm2-plus-michelin/p/cb64ff955b/au/pine/",
    "data_coleta": "2025-08-11 19:53:05",
    "medida": "195/60R15",
    "marca": "michelin",
    "modelo": "energy xm2",
    "preco_original": 68307975.9,
    "promocao": true,
    "imagem": "https://a-static.mlcdn.com.br/280x210/pneu-aro-15-195-60r15-88v-energy-xm2-plus-michelin/pneubaratocombr/19248/9d22b5d9298a67b175cde9811ab65975.jpeg",
    "marketplace": "magazineluiza",
    "categoria": "",
    "disponivel": true,
    "avaliacoes": 0,
    "nota_media": 0.0,
    "vendedor": "Pneu Barato",
    "frete_gratis": false,
    "parcelamento": "",
    "descricao": "",
    "frete": null
  },
  {
    "titulo": "Pneu Michelin Aro 15 Energy XM2+ 195/60R15 88V",
    "preco": 596.39,
    "link": "https://www.magazineluiza.com.br/pneu-michelin-aro-15-energy-xm2-195-60r15-88v/p/ffehj020k9/au/aupa/",
    "data_coleta": "2025-08-11 19:53:13",
    "medida": "195/60R15",
    "marca": "michelin",
    "modelo": "energy xm2",
    "preco_original": 720.53,
    "promocao": true,
    "imagem": "https://a-static.mlcdn.com.br/280x210/pneu-michelin-aro-15-energy-xm2-195-60r15-88v/pneustore/10110158/74026b318f4c5eb6f3ff8b71ea1fb723.jpeg",
    "marketplace": "magazineluiza",
    "categoria": "",
    "disponivel": true,
    "avaliacoes": 88,
    "nota_media": 8.0,
    "vendedor": "PneuStore",
    "frete_gratis": false,
    "parcelamento": "",
    "descricao": "",
    "frete": null
  },
  {
    "titulo": "Pneu Aro 15 Michelin 195/60 R15 88V TL ENERGY XM2+",
    "preco": 681.35,
    "link": "https://www.magazineluiza.com.br/pneu-aro-15-michelin-195-60-r15-88v-tl-energy-xm2/p/jkkda58kf6/au/aupa/",
    "data_coleta": "2025-08-11 19:53:19",
    "medida": "195/60R15",
    "marca": "michelin",
    "modelo": "energy xm2",
    "preco_original": 745.37,
    "promocao": true,
    "imagem": "https://a-static.mlcdn.com.br/280x210/pneu-aro-15-michelin-195-60-r15-88v-tl-energy-xm2/pneugreen/199/aadef8c00b32a122349a64a0b814339d.jpeg",
    "marketplace": "magazineluiza",
    "categoria": "",
    "disponivel": true,
    "avaliacoes": 88,
    "nota_media": 8.0,
    "vendedor": "Pneugreen",
    "frete_gratis": false,
    "parcelamento": "",
    "descricao": "",
    "frete": null
  },
  {
    "titulo": "Pneu Michelin Aro 15 195/60R15 Energy XM2 88V",
    "preco": 892.15,
    "link": "https://www.magazineluiza.com.br/pneu-michelin-aro-15-195-60r15-energy-xm2-88v/p/he2k2dj23b/au/aupa/",
    "data_coleta": "2025-08-11 19:53:29",
    "medida": "195/60R15",
    "marca": "michelin",
    "modelo": "energy xm2",
    "preco_original": 939111278.26,
    "promocao": true,
    "imagem": "https://a-static.mlcdn.com.br/280x210/pneu-michelin-aro-15-195-60r15-energy-xm2-88v/webpneus/37008/4c57801c154581450131810e95ed3cf3.jpeg",
    "marketplace": "magazineluiza",
    "categoria": "",
    "disponivel": true,
    "avaliacoes": 88,
    "nota_media": 8.0,
    "vendedor": "Web Pneus",
    "frete_gratis": false,
    "parcelamento": "",
    "descricao": "",
    "frete": null
  },
  {
    "titulo": "Pneu Michelin Aro 15 195/60R15 Energy XM2 88V",
    "preco": 892.15,
    "link": "https://www.magazineluiza.com.br/pneu-michelin-aro-15-195-60r15-energy-xm2-88v/p/he2k2dj23b/au/aupa/?seller_id=webpneus",
    "data_coleta": "2025-08-11 19:53:44",
    "medida": "195/60R15",
    "marca": "michelin",
    "modelo": "energy xm2",
    "preco_original": 939111278.26,
    "promocao": true,
    "imagem": "https://a-static.mlcdn.com.br/280x210/pneu-michelin-aro-15-195-60r15-energy-xm2-88v/webpneus/37008/4c57801c154581450131810e95ed3cf3.jpeg",
    "marketplace": "magazineluiza",
    "categoria": "",
    "disponivel": true,
    "avaliacoes": 88,
    "nota_media": 0.0,
    "vendedor": "Web Pneus",
    "frete_gratis": false,
    "parcelamento": "",
    "descricao": "",
    "frete": null
  },
  {
    "titulo": "Pneu Aro 15 Michelin 195/60 R15 88V TL ENERGY XM2+",
    "preco": 681.35,
    "link": "https://www.magazineluiza.com.br/pneu-aro-15-michelin-195-60-r15-88v-tl-energy-xm2/p/jkkda58kf6/au/aupa/?seller_id=pneugreen",
    "data_coleta": "2025-08-11 19:53:50",
    "medida": "195/60R15",
    "marca": "michelin",
    "modelo": "energy xm2",
    "preco_original": 745.37,
    "promocao": true,
    "imagem": "https://a-static.mlcdn.com.br/280x210/pneu-aro-15-michelin-195-60-r15-88v-tl-energy-xm2/pneugreen/199/aadef8c00b32a122349a64a0b814339d.jpeg",
    "marketplace": "magazineluiza",
    "categoria": "",
    "disponivel": true,
    "avaliacoes": 88,
    "nota_media": 0.0,
    "vendedor": "Pneugreen",
    "frete_gratis": false,
    "parcelamento": "",
    "descricao": "",
    "frete": null
  },
  {
    "titulo": "Pneu Michelin Aro 15 Energy XM2+ 195/60R15 88V",
    "preco": 596.39,
    "link": "https://www.magazineluiza.com.br/pneu-michelin-aro-15-energy-xm2-195-60r15-88v/p/ffehj020k9/au/aupa/?seller_id=pneustore",
    "data_coleta": "2025-08-11 19:53:58",
    "medida": "195/60R15",
    "marca": "michelin",
    "modelo": "energy xm2",
    "preco_original": 720.53,
    "promocao": true,
    "imagem": "https://a-static.mlcdn.com.br/280x210/pneu-michelin-aro-15-energy-xm2-195-60r15-88v/pneustore/10110158/74026b318f4c5eb6f3ff8b71ea1fb723.jpeg",
    "marketplace": "magazineluiza",
    "categoria": "",
    "disponivel": true,
    "avaliacoes": 88,
    "nota_media": 0.0,
    "vendedor": "PneuStore",
    "frete_gratis": false,
    "parcelamento": "",
    "descricao": "",
    "frete": null
  },
  {
    "titulo": "Pneu Aro 15 195/60R15 88V Energy XM2 Plus Michelin",
    "preco": 580.61,
    "link": "https://www.magazineluiza.com.br/pneu-aro-15-195-60r15-88v-energy-xm2-plus-michelin/p/cb64ff955b/au/pine/?seller_id=pneubaratocombr",
    "data_coleta": "2025-08-11 19:54:04",
    "medida": "195/60R15",
    "marca": "michelin",
    "modelo": "energy xm2",
    "preco_original": 68307975.9,
    "promocao": true,
    "imagem": "https://a-static.mlcdn.com.br/280x210/pneu-aro-15-195-60r15-88v-energy-xm2-plus-michelin/pneubaratocombr/19248/9d22b5d9298a67b175cde9811ab65975.jpeg",
    "marketplace": "magazineluiza",
    "categoria": "",
    "disponivel": true,
    "avaliacoes": 0,
    "nota_media": 0.0,
    "vendedor": "Pneu Barato",
    "frete_gratis": false,
    "parcelamento": "",
    "descricao": "",
    "frete": null
  },
  {
    "titulo": "Pneu Aro 15 195/60R15 88V Energy XM2 Plus Michelin",
    "preco": 580.61,
    "link": "https://www.magazineluiza.com.br/pneu-aro-15-195-60r15-88v-energy-xm2-plus-michelin/p/cb64ff955b/au/pine/?seller_id=pneubaratocombr",
    "data_coleta": "2025-08-11 19:54:15",
    "medida": "195/60R15",
    "marca": "michelin",
    "modelo": "energy xm2",
    "preco_original": 68307975.9,
    "promocao": true,
    "imagem": "https://a-static.mlcdn.com.br/280x210/pneu-aro-15-195-60r15-88v-energy-xm2-plus-michelin/pneubaratocombr/19248/9d22b5d9298a67b175cde9811ab65975.jpeg",
    "marketplace": "magazineluiza",
    "categoria": "",
    "disponivel": true,
    "avaliacoes": 0,
    "nota_media": 0.0,
    "vendedor": "Pneu Barato",
    "frete_gratis": false,
    "parcelamento": "",
    "descricao": "",
    "frete": null
  },
  {
    "titulo": "Pneu Aro 15 195/60R15 88V Energy XM2 Plus Michelin",
    "preco": 580.61,
    "link": "https://www.magazineluiza.com.br/pneu-aro-15-195-60r15-88v-energy-xm2-plus-michelin/p/cb64ff955b/au/pine/",
    "data_coleta": "2025-08-11 19:54:42",
    "medida": "195/60R15",
    "marca": "michelin",
    "modelo": "energy xm2",
    "preco_original": 68307975.9,
    "promocao": true,
    "imagem": "https://a-static.mlcdn.com.br/280x210/pneu-aro-15-195-60r15-88v-energy-xm2-plus-michelin/pneubaratocombr/19248/9d22b5d9298a67b175cde9811ab65975.jpeg",
    "marketplace": "magazineluiza",
    "categoria": "",
    "disponivel": true,
    "avaliacoes": 0,
    "nota_media": 0.0,
    "vendedor": "Pneu Barato",
    "frete_gratis": false,
    "parcelamento": "",
    "descricao": "",
    "frete": null
  },
  {
    "titulo": "Pneu Michelin Aro 15 Energy XM2+ 195/60R15 88V",
    "preco": 596.39,
    "link": "https://www.magazineluiza.com.br/pneu-michelin-aro-15-energy-xm2-195-60r15-88v/p/ffehj020k9/au/aupa/",
    "data_coleta": "2025-08-11 19:54:51",
    "medida": "195/60R15",
    "marca": "michelin",
    "modelo": "energy xm2",
    "preco_original": 720.53,
    "promocao": true,
    "imagem": "https://a-static.mlcdn.com.br/280x210/pneu-michelin-aro-15-energy-xm2-195-60r15-88v/pneustore/10110158/74026b318f4c5eb6f3ff8b71ea1fb723.jpeg",
    "marketplace": "magazineluiza",
    "categoria": "",
    "disponivel": true,
    "avaliacoes": 88,
    "nota_media": 8.0,
    "vendedor": "PneuStore",
    "frete_gratis": false,
    "parcelamento": "",
    "descricao": "",
    "frete": null
  },
  {
    "titulo": "Pneu Aro 15 Michelin 195/60 R15 88V TL ENERGY XM2+",
    "preco": 681.35,
    "link": "https://www.magazineluiza.com.br/pneu-aro-15-michelin-195-60-r15-88v-tl-energy-xm2/p/jkkda58kf6/au/aupa/",
    "data_coleta": "2025-08-11 19:54:57",
    "medida": "195/60R15",
    "marca": "michelin",
    "modelo": "energy xm2",
    "preco_original": 745.37,
    "promocao": true,
    "imagem": "https://a-static.mlcdn.com.br/280x210/pneu-aro-15-michelin-195-60-r15-88v-tl-energy-xm2/pneugreen/199/aadef8c00b32a122349a64a0b814339d.jpeg",
    "marketplace": "magazineluiza",
    "categoria": "",
    "disponivel": true,
    "avaliacoes": 88,
    "nota_media": 8.0,
    "vendedor": "Pneugreen",
    "frete_gratis": false,
    "parcelamento": "",
    "descricao": "",
    "frete": null
  },
  {
    "titulo": "Pneu Michelin Aro 15 195/60R15 Energy XM2 88V",
    "preco": 892.15,
    "link": "https://www.magazineluiza.com.br/pneu-michelin-aro-15-195-60r15-energy-xm2-88v/p/he2k2dj23b/au/aupa/",
    "data_coleta": "2025-08-11 19:55:09",
    "medida": "195/60R15",
    "marca": "michelin",
    "modelo": "energy xm2",
    "preco_original": 939111278.26,
    "promocao": true,
    "imagem": "https://a-static.mlcdn.com.br/280x210/pneu-michelin-aro-15-195-60r15-energy-xm2-88v/webpneus/37008/4c57801c154581450131810e95ed3cf3.jpeg",
    "marketplace": "magazineluiza",
    "categoria": "",
    "disponivel": true,
    "avaliacoes": 88,
    "nota_media": 8.0,
    "vendedor": "Web Pneus",
    "frete_gratis": false,
    "parcelamento": "",
    "descricao": "",
    "frete": null
  },
  {
    "titulo": "Pneu Aro 15 195/60R15 88V Energy XM2 Plus Michelin",
    "preco": 580.61,
    "link": "https://www.magazineluiza.com.br/pneu-aro-15-195-60r15-88v-energy-xm2-plus-michelin/p/cb64ff955b/au/pine/?seller_id=pneubaratocombr",
    "data_coleta": "2025-08-11 19:55:21",
    "medida": "195/60R15",
    "marca": "michelin",
    "modelo": "energy xm2",
    "preco_original": 68307975.9,
    "promocao": true,
    "imagem": "https://a-static.mlcdn.com.br/280x210/pneu-aro-15-195-60r15-88v-energy-xm2-plus-michelin/pneubaratocombr/19248/9d22b5d9298a67b175cde9811ab65975.jpeg",
    "marketplace": "magazineluiza",
    "categoria": "",
    "disponivel": true,
    "avaliacoes": 0,
    "nota_media": 0.0,
    "vendedor": "Pneu Barato",
    "frete_gratis": false,
    "parcelamento": "",
    "descricao": "",
    "frete": null
  },
  {
    "titulo": "Pneu Michelin Aro 15 Energy XM2+ 195/60R15 88V",
    "preco": 596.39,
    "link": "https://www.magazineluiza.com.br/pneu-michelin-aro-15-energy-xm2-195-60r15-88v/p/ffehj020k9/au/aupa/?seller_id=pneustore",
    "data_coleta": "2025-08-11 19:55:31",
    "medida": "195/60R15",
    "marca": "michelin",
    "modelo": "energy xm2",
    "preco_original": 720.53,
    "promocao": true,
    "imagem": "https://a-static.mlcdn.com.br/280x210/pneu-michelin-aro-15-energy-xm2-195-60r15-88v/pneustore/10110158/74026b318f4c5eb6f3ff8b71ea1fb723.jpeg",
    "marketplace": "magazineluiza",
    "categoria": "",
    "disponivel": true,
    "avaliacoes": 88,
    "nota_media": 0.0,
    "vendedor": "PneuStore",
    "frete_gratis": false,
    "parcelamento": "",
    "descricao": "",
    "frete": null
  },
  {
    "titulo": "Pneu Aro 15 Michelin 195/60 R15 88V TL ENERGY XM2+",
    "preco": 681.35,
    "link": "https://www.magazineluiza.com.br/pneu-aro-15-michelin-195-60-r15-88v-tl-energy-xm2/p/jkkda58kf6/au/aupa/?seller_id=pneugreen",
    "data_coleta": "2025-08-11 19:55:37",
    "medida": "195/60R15",
    "marca": "michelin",
    "modelo": "energy xm2",
    "preco_original": 745.37,
    "promocao": true,
    "imagem": "https://a-static.mlcdn.com.br/280x210/pneu-aro-15-michelin-195-60-r15-88v-tl-energy-xm2/pneugreen/199/aadef8c00b32a122349a64a0b814339d.jpeg",
    "marketplace": "magazineluiza",
    "categoria": "",
    "disponivel": true,
    "avaliacoes": 88,
    "nota_media": 0.0,
    "vendedor": "Pneugreen",
    "frete_gratis": false,
    "parcelamento": "",
    "descricao": "",
    "frete": null
  },
  {
    "titulo": "Pneu Michelin Aro 15 195/60R15 Energy XM2 88V",
    "preco": 892.15,
    "link": "https://www.magazineluiza.com.br/pneu-michelin-aro-15-195-60r15-energy-xm2-88v/p/he2k2dj23b/au/aupa/?seller_id=webpneus",
    "data_coleta": "2025-08-11 19:55:44",
    "medida": "195/60R15",
    "marca": "michelin",
    "modelo": "energy xm2",
    "preco_original": 939111278.26,
    "promocao": true,
    "imagem": "https://a-static.mlcdn.com.br/280x210/pneu-michelin-aro-15-195-60r15-energy-xm2-88v/webpneus/37008/4c57801c154581450131810e95ed3cf3.jpeg",
    "marketplace": "magazineluiza",
    "categoria": "",
    "disponivel": true,
    "avaliacoes": 88,
    "nota_media": 0.0,
    "vendedor": "Web Pneus",
    "frete_gratis": false,
    "parcelamento": "",
    "descricao": "",
    "frete": null
  }
]