[
  {
    "titulo": "Pneu Aro 16\" 205/60R16 Goodyear 92H Wrangler Territory HT",
    "preco": 659.9,
    "link": "https://www.magazineluiza.com.br/pneu-aro-16-205-60r16-goodyear-92h-wrangler-territory-ht/p/240116000/au/pine/",
    "data_coleta": "2025-08-14 17:09:35",
    "medida": "205/60R16",
    "marca": "goodyear",
    "modelo": "wrangler",
    "preco_original": 999.9,
    "promocao": true,
    "imagem": "https://a-static.mlcdn.com.br/280x210/pneu-aro-16-205-60r16-goodyear-92h-wrangler-territory-ht/magazineluiza/240116000/e5347e8e95fe4952ed9c6faf8fa47775.jpg",
    "marketplace": "magazineluiza",
    "categoria": "",
    "disponivel": true,
    "avaliacoes": 1,
    "nota_media": 0.0,
    "vendedor": "magazineluiza",
    "frete_gratis": false,
    "parcelamento": "",
    "descricao": "",
    "frete": null
  },
  {
    "titulo": "Pneu Goodyear Aro 16 205/60R16 Wrangler Territory HT 92H",
    "preco": 1084.74,
    "link": "https://www.magazineluiza.com.br/pneu-goodyear-aro-16-205-60r16-wrangler-territory-ht-92h/p/ec63ghah95/au/aupa/",
    "data_coleta": "2025-08-14 17:09:43",
    "medida": "205/60R16",
    "marca": "goodyear",
    "modelo": "wrangler",
    "preco_original": 1141831295.15,
    "promocao": true,
    "imagem": "https://a-static.mlcdn.com.br/280x210/pneu-goodyear-aro-16-205-60r16-wrangler-territory-ht-92h/webpneus/36013/0814687b94a804070317143bf1cd0677.jpeg",
    "marketplace": "magazineluiza",
    "categoria": "",
    "disponivel": true,
    "avaliacoes": 2,
    "nota_media": 5.0,
    "vendedor": "Web Pneus",
    "frete_gratis": false,
    "parcelamento": "",
    "descricao": "",
    "frete": null
  },
  {
    "titulo": "Pneu 205/60R16 Goodyear Wrangler Territory HT 92H Aro 16",
    "preco": 835.0,
    "link": "https://www.magazineluiza.com.br/pneu-205-60r16-goodyear-wrangler-territory-ht-92h-aro-16/p/jej49b89kh/au/aupa/",
    "data_coleta": "2025-08-14 17:09:46",
    "medida": "205/60R16",
    "marca": "goodyear",
    "modelo": "wrangler",
    "preco_original": 907611090.76,
    "promocao": true,
    "imagem": "https://a-static.mlcdn.com.br/280x210/pneu-205-60r16-goodyear-wrangler-territory-ht-92h-aro-16/lojaacheipneus/36775/4c30bfeda74261fdd8d2ffe304a64800.jpeg",
    "marketplace": "magazineluiza",
    "categoria": "",
    "disponivel": true,
    "avaliacoes": 1,
    "nota_media": 0.0,
    "vendedor": "Achei Pneus",
    "frete_gratis": false,
    "parcelamento": "",
    "descricao": "",
    "frete": null
  },
  {
    "titulo": "Pneu Goodyear Aro 16 Wrangler Territory HT 205/60R16 92H",
    "preco": 788.78,
    "link": "https://www.magazineluiza.com.br/pneu-goodyear-aro-16-wrangler-territory-ht-205-60r16-92h/p/ha1g1hec7h/au/aupa/",
    "data_coleta": "2025-08-14 17:09:51",
    "medida": "205/60R16",
    "marca": "goodyear",
    "modelo": "wrangler",
    "preco_original": 788781078.88,
    "promocao": true,
    "imagem": "https://a-static.mlcdn.com.br/280x210/pneu-goodyear-aro-16-wrangler-territory-ht-205-60r16-92h/pneustore/16010631/57c6d669a98b17e1b43828b154c3660c.jpeg",
    "marketplace": "magazineluiza",
    "categoria": "",
    "disponivel": true,
    "avaliacoes": 1,
    "nota_media": 0.0,
    "vendedor": "PneuStore",
    "frete_gratis": false,
    "parcelamento": "",
    "descricao": "",
    "frete": null
  },
  {
    "titulo": "Pneu 205 60R16 Wrangler Fortitude Ht Goodyear 92H SL HT",
    "preco": 788.41,
    "link": "https://www.magazineluiza.com.br/pneu-205-60r16-wrangler-fortitude-ht-goodyear-92h-sl-ht/p/gh68je8dbk/au/aupa/",
    "data_coleta": "2025-08-14 17:09:54",
    "medida": "205/60R16",
    "marca": "goodyear",
    "modelo": "wrangler",
    "preco_original": 829901175.45,
    "promocao": true,
    "imagem": "https://a-static.mlcdn.com.br/280x210/pneu-205-60r16-wrangler-fortitude-ht-goodyear-92h-sl-ht/carrefouroficial/900012955/81f9128495a04a5900a42968ad684f18.jpeg",
    "marketplace": "magazineluiza",
    "categoria": "",
    "disponivel": true,
    "avaliacoes": 1,
    "nota_media": 0.0,
    "vendedor": "Carrefour Oficial",
    "frete_gratis": false,
    "parcelamento": "",
    "descricao": "",
    "frete": null
  },
  {
    "titulo": "Pneu 205/60R16 Goodyear Wrangler Territory HT 92H",
    "preco": 888.41,
    "link": "https://www.magazineluiza.com.br/pneu-205-60r16-goodyear-wrangler-territory-ht-92h/p/kh9adc7aa9/au/aupa/",
    "data_coleta": "2025-08-14 17:09:58",
    "medida": "205/60R16",
    "marca": "goodyear",
    "modelo": "wrangler",
    "preco_original": 935171093.52,
    "promocao": true,
    "imagem": "https://a-static.mlcdn.com.br/280x210/pneu-205-60r16-goodyear-wrangler-territory-ht-92h/pneustyres/2649584/eabddbd2d84fa0110614a969cc1f9163.jpeg",
    "marketplace": "magazineluiza",
    "categoria": "",
    "disponivel": true,
    "avaliacoes": 5,
    "nota_media": 2.0,
    "vendedor": "Pneustyres",
    "frete_gratis": false,
    "parcelamento": "",
    "descricao": "",
    "frete": null
  },
  {
    "titulo": "Pneu Aro 16\" 205/60R16 Goodyear 92H Wrangler Territory HT",
    "preco": 659.9,
    "link": "https://www.magazineluiza.com.br/pneu-aro-16-205-60r16-goodyear-92h-wrangler-territory-ht/p/240116000/au/pine/",
    "data_coleta": "2025-08-14 17:10:36",
    "medida": "205/60R16",
    "marca": "goodyear",
    "modelo": "wrangler",
    "preco_original": 999.9,
    "promocao": true,
    "imagem": "https://a-static.mlcdn.com.br/280x210/pneu-aro-16-205-60r16-goodyear-92h-wrangler-territory-ht/magazineluiza/240116000/e5347e8e95fe4952ed9c6faf8fa47775.jpg",
    "marketplace": "magazineluiza",
    "categoria": "",
    "disponivel": true,
    "avaliacoes": 1,
    "nota_media": 0.0,
    "vendedor": "magazineluiza",
    "frete_gratis": false,
    "parcelamento": "",
    "descricao": "",
    "frete": null
  },
  {
    "titulo": "Pneu Goodyear Aro 16 205/60R16 Wrangler Territory HT 92H",
    "preco": 1084.74,
    "link": "https://www.magazineluiza.com.br/pneu-goodyear-aro-16-205-60r16-wrangler-territory-ht-92h/p/ec63ghah95/au/aupa/",
    "data_coleta": "2025-08-14 17:10:39",
    "medida": "205/60R16",
    "marca": "goodyear",
    "modelo": "wrangler",
    "preco_original": 1141831295.15,
    "promocao": true,
    "imagem": "https://a-static.mlcdn.com.br/280x210/pneu-goodyear-aro-16-205-60r16-wrangler-territory-ht-92h/webpneus/36013/0814687b94a804070317143bf1cd0677.jpeg",
    "marketplace": "magazineluiza",
    "categoria": "",
    "disponivel": true,
    "avaliacoes": 2,
    "nota_media": 5.0,
    "vendedor": "Web Pneus",
    "frete_gratis": false,
    "parcelamento": "",
    "descricao": "",
    "frete": null
  },
  {
    "titulo": "Pneu 205/60R16 Goodyear Wrangler Territory HT 92H Aro 16",
    "preco": 835.0,
    "link": "https://www.magazineluiza.com.br/pneu-205-60r16-goodyear-wrangler-territory-ht-92h-aro-16/p/jej49b89kh/au/aupa/",
    "data_coleta": "2025-08-14 17:10:41",
    "medida": "205/60R16",
    "marca": "goodyear",
    "modelo": "wrangler",
    "preco_original": 907611090.76,
    "promocao": true,
    "imagem": "https://a-static.mlcdn.com.br/280x210/pneu-205-60r16-goodyear-wrangler-territory-ht-92h-aro-16/lojaacheipneus/36775/4c30bfeda74261fdd8d2ffe304a64800.jpeg",
    "marketplace": "magazineluiza",
    "categoria": "",
    "disponivel": true,
    "avaliacoes": 1,
    "nota_media": 0.0,
    "vendedor": "Achei Pneus",
    "frete_gratis": false,
    "parcelamento": "",
    "descricao": "",
    "frete": null
  },
  {
    "titulo": "Pneu Goodyear Aro 16 Wrangler Territory HT 205/60R16 92H",
    "preco": 788.78,
    "link": "https://www.magazineluiza.com.br/pneu-goodyear-aro-16-wrangler-territory-ht-205-60r16-92h/p/ha1g1hec7h/au/aupa/",
    "data_coleta": "2025-08-14 17:10:45",
    "medida": "205/60R16",
    "marca": "goodyear",
    "modelo": "wrangler",
    "preco_original": 788781078.88,
    "promocao": true,
    "imagem": "https://a-static.mlcdn.com.br/280x210/pneu-goodyear-aro-16-wrangler-territory-ht-205-60r16-92h/pneustore/16010631/57c6d669a98b17e1b43828b154c3660c.jpeg",
    "marketplace": "magazineluiza",
    "categoria": "",
    "disponivel": true,
    "avaliacoes": 1,
    "nota_media": 0.0,
    "vendedor": "PneuStore",
    "frete_gratis": false,
    "parcelamento": "",
    "descricao": "",
    "frete": null
  },
  {
    "titulo": "Pneu 205 60R16 Wrangler Fortitude Ht Goodyear 92H SL HT",
    "preco": 788.41,
    "link": "https://www.magazineluiza.com.br/pneu-205-60r16-wrangler-fortitude-ht-goodyear-92h-sl-ht/p/gh68je8dbk/au/aupa/",
    "data_coleta": "2025-08-14 17:10:47",
    "medida": "205/60R16",
    "marca": "goodyear",
    "modelo": "wrangler",
    "preco_original": 829901175.45,
    "promocao": true,
    "imagem": "https://a-static.mlcdn.com.br/280x210/pneu-205-60r16-wrangler-fortitude-ht-goodyear-92h-sl-ht/carrefouroficial/900012955/81f9128495a04a5900a42968ad684f18.jpeg",
    "marketplace": "magazineluiza",
    "categoria": "",
    "disponivel": true,
    "avaliacoes": 1,
    "nota_media": 0.0,
    "vendedor": "Carrefour Oficial",
    "frete_gratis": false,
    "parcelamento": "",
    "descricao": "",
    "frete": null
  },
  {
    "titulo": "Pneu 205/60R16 Goodyear Wrangler Territory HT 92H",
    "preco": 888.41,
    "link": "https://www.magazineluiza.com.br/pneu-205-60r16-goodyear-wrangler-territory-ht-92h/p/kh9adc7aa9/au/aupa/",
    "data_coleta": "2025-08-14 17:10:49",
    "medida": "205/60R16",
    "marca": "goodyear",
    "modelo": "wrangler",
    "preco_original": 935171093.52,
    "promocao": true,
    "imagem": "https://a-static.mlcdn.com.br/280x210/pneu-205-60r16-goodyear-wrangler-territory-ht-92h/pneustyres/2649584/eabddbd2d84fa0110614a969cc1f9163.jpeg",
    "marketplace": "magazineluiza",
    "categoria": "",
    "disponivel": true,
    "avaliacoes": 5,
    "nota_media": 2.0,
    "vendedor": "Pneustyres",
    "frete_gratis": false,
    "parcelamento": "",
    "descricao": "",
    "frete": null
  },
  {
    "titulo": "Pneu 205/60R16 Goodyear Wrangler Territory HT 92H",
    "preco": 888.41,
    "link": "https://www.magazineluiza.com.br/pneu-205-60r16-goodyear-wrangler-territory-ht-92h/p/kh9adc7aa9/au/aupa/?seller_id=pneustyres",
    "data_coleta": "2025-08-14 17:10:57",
    "medida": "205/60R16",
    "marca": "goodyear",
    "modelo": "wrangler",
    "preco_original": 935171093.52,
    "promocao": true,
    "imagem": "https://a-static.mlcdn.com.br/280x210/pneu-205-60r16-goodyear-wrangler-territory-ht-92h/pneustyres/2649584/eabddbd2d84fa0110614a969cc1f9163.jpeg",
    "marketplace": "magazineluiza",
    "categoria": "",
    "disponivel": true,
    "avaliacoes": 5,
    "nota_media": 0.0,
    "vendedor": "Pneustyres",
    "frete_gratis": false,
    "parcelamento": "",
    "descricao": "",
    "frete": null
  },
  {
    "titulo": "Pneu 205 60R16 Wrangler Fortitude Ht Goodyear 92H SL HT",
    "preco": 788.41,
    "link": "https://www.magazineluiza.com.br/pneu-205-60r16-wrangler-fortitude-ht-goodyear-92h-sl-ht/p/gh68je8dbk/au/aupa/?seller_id=carrefouroficial",
    "data_coleta": "2025-08-14 17:11:00",
    "medida": "205/60R16",
    "marca": "goodyear",
    "modelo": "wrangler",
    "preco_original": 829901175.45,
    "promocao": true,
    "imagem": "https://a-static.mlcdn.com.br/280x210/pneu-205-60r16-wrangler-fortitude-ht-goodyear-92h-sl-ht/carrefouroficial/900012955/81f9128495a04a5900a42968ad684f18.jpeg",
    "marketplace": "magazineluiza",
    "categoria": "",
    "disponivel": true,
    "avaliacoes": 1,
    "nota_media": 0.0,
    "vendedor": "Carrefour Oficial",
    "frete_gratis": false,
    "parcelamento": "",
    "descricao": "",
    "frete": null
  },
  {
    "titulo": "Pneu 205 60R16 Wrangler Fortitude Ht Goodyear 92H SL HT",
    "preco": 788.41,
    "link": "https://www.magazineluiza.com.br/pneu-205-60r16-wrangler-fortitude-ht-goodyear-92h-sl-ht/p/gh68je8dbk/au/aupa/?seller_id=carrefouroficial",
    "data_coleta": "2025-08-14 17:11:06",
    "medida": "205/60R16",
    "marca": "goodyear",
    "modelo": "wrangler",
    "preco_original": 829901175.45,
    "promocao": true,
    "imagem": "https://a-static.mlcdn.com.br/280x210/pneu-205-60r16-wrangler-fortitude-ht-goodyear-92h-sl-ht/carrefouroficial/900012955/81f9128495a04a5900a42968ad684f18.jpeg",
    "marketplace": "magazineluiza",
    "categoria": "",
    "disponivel": true,
    "avaliacoes": 1,
    "nota_media": 0.0,
    "vendedor": "Carrefour Oficial",
    "frete_gratis": false,
    "parcelamento": "",
    "descricao": "",
    "frete": null
  },
  {
    "titulo": "Pneu 205/60R16 Goodyear Wrangler Territory HT 92H Aro 16",
    "preco": 835.0,
    "link": "https://www.magazineluiza.com.br/pneu-205-60r16-goodyear-wrangler-territory-ht-92h-aro-16/p/jej49b89kh/au/aupa/?seller_id=lojaacheipneus",
    "data_coleta": "2025-08-14 17:11:15",
    "medida": "205/60R16",
    "marca": "goodyear",
    "modelo": "wrangler",
    "preco_original": 907611090.76,
    "promocao": true,
    "imagem": "https://a-static.mlcdn.com.br/280x210/pneu-205-60r16-goodyear-wrangler-territory-ht-92h-aro-16/lojaacheipneus/36775/4c30bfeda74261fdd8d2ffe304a64800.jpeg",
    "marketplace": "magazineluiza",
    "categoria": "",
    "disponivel": true,
    "avaliacoes": 1,
    "nota_media": 0.0,
    "vendedor": "Achei Pneus",
    "frete_gratis": false,
    "parcelamento": "",
    "descricao": "",
    "frete": null
  },
  {
    "titulo": "Pneu Goodyear Aro 16 Wrangler Territory HT 205/60R16 92H",
    "preco": 788.78,
    "link": "https://www.magazineluiza.com.br/pneu-goodyear-aro-16-wrangler-territory-ht-205-60r16-92h/p/ha1g1hec7h/au/aupa/?seller_id=pneustore",
    "data_coleta": "2025-08-14 17:11:18",
    "medida": "205/60R16",
    "marca": "goodyear",
    "modelo": "wrangler",
    "preco_original": 788781078.88,
    "promocao": true,
    "imagem": "https://a-static.mlcdn.com.br/280x210/pneu-goodyear-aro-16-wrangler-territory-ht-205-60r16-92h/pneustore/16010631/57c6d669a98b17e1b43828b154c3660c.jpeg",
    "marketplace": "magazineluiza",
    "categoria": "",
    "disponivel": true,
    "avaliacoes": 1,
    "nota_media": 0.0,
    "vendedor": "PneuStore",
    "frete_gratis": false,
    "parcelamento": "",
    "descricao": "",
    "frete": null
  },
  {
    "titulo": "Pneu Aro 16\" 205/60R16 Goodyear 92H Wrangler Territory HT",
    "preco": 659.9,
    "link": "https://www.magazineluiza.com.br/pneu-aro-16-205-60r16-goodyear-92h-wrangler-territory-ht/p/240116000/au/pine/?seller_id=magazineluiza",
    "data_coleta": "2025-08-14 17:11:30",
    "medida": "205/60R16",
    "marca": "goodyear",
    "modelo": "wrangler",
    "preco_original": 999.9,
    "promocao": true,
    "imagem": "https://a-static.mlcdn.com.br/280x210/pneu-aro-16-205-60r16-goodyear-92h-wrangler-territory-ht/magazineluiza/240116000/e5347e8e95fe4952ed9c6faf8fa47775.jpg",
    "marketplace": "magazineluiza",
    "categoria": "",
    "disponivel": true,
    "avaliacoes": 1,
    "nota_media": 0.0,
    "vendedor": "magazineluiza",
    "frete_gratis": false,
    "parcelamento": "",
    "descricao": "",
    "frete": null
  }
]