[
  {
    "titulo": "Pneu Aro 15 Goodyear EfficientGrip Performance 195/55R15 85H",
    "preco": 555.24,
    "link": "https://www.magazineluiza.com.br/pneu-aro-15-goodyear-efficientgrip-performance-195-55r15-85h/p/7515101/au/pine/",
    "data_coleta": "2025-08-08 19:09:39",
    "preco_original": 659.75,
    "promocao": true,
    "imagem": "https://a-static.mlcdn.com.br/280x210/pneu-aro-15-goodyear-efficientgrip-performance-195-55r15-85h/pneustore/10130137/3629cac27779ce6c7af8764746c02944.jpeg",
    "marketplace": "magazineluiza",
    "categoria": "",
    "disponivel": true,
    "avaliacoes": 15,
    "nota_media": 9.0,
    "vendedor": "PneuStore",
    "frete_gratis": false,
    "parcelamento": "",
    "descricao": "",
    "frete": null
  },
  {
    "titulo": "Pneu Goodyear 195/55 R15 85H SL Efficientgrip Performance",
    "preco": 567.63,
    "link": "https://www.magazineluiza.com.br/pneu-goodyear-195-55-r15-85h-sl-efficientgrip-performance/p/ddh0d02875/au/aupa/",
    "data_coleta": "2025-08-08 19:09:45",
    "preco_original": 632.65,
    "promocao": true,
    "imagem": "https://a-static.mlcdn.com.br/280x210/pneu-goodyear-195-55-r15-85h-sl-efficientgrip-performance/pneugreen/1792/37a1f64e2df9213c5cf34cd715847d37.jpeg",
    "marketplace": "magazineluiza",
    "categoria": "",
    "disponivel": true,
    "avaliacoes": 31,
    "nota_media": 8.0,
    "vendedor": "Pneugreen",
    "frete_gratis": false,
    "parcelamento": "",
    "descricao": "",
    "frete": null
  },
  {
    "titulo": "Pneu Goodyear Aro 15 195/55R15 Efficientgrip 85H",
    "preco": 864.49,
    "link": "https://www.magazineluiza.com.br/pneu-goodyear-aro-15-195-55r15-efficientgrip-85h/p/bc00655h64/au/pine/",
    "data_coleta": "2025-08-08 19:09:51",
    "preco_original": 909991275.83,
    "promocao": true,
    "imagem": "https://a-static.mlcdn.com.br/280x210/pneu-goodyear-aro-15-195-55r15-efficientgrip-85h/webpneus/29442/9fb607d444ef3d76ca7e9a4338c34793.jpeg",
    "marketplace": "magazineluiza",
    "categoria": "",
    "disponivel": true,
    "avaliacoes": 2731,
    "nota_media": 8.0,
    "vendedor": "Web Pneus",
    "frete_gratis": false,
    "parcelamento": "",
    "descricao": "",
    "frete": null
  },
  {
    "titulo": "Pneu 195/55R15 Goodyear Efficientgrip Performance 85H",
    "preco": 650.03,
    "link": "https://www.magazineluiza.com.br/pneu-195-55r15-goodyear-efficientgrip-performance-85h/p/efjh76beh4/au/pine/",
    "data_coleta": "2025-08-08 19:09:58",
    "preco_original": 727.18,
    "promocao": true,
    "imagem": "https://a-static.mlcdn.com.br/280x210/pneu-195-55r15-goodyear-efficientgrip-performance-85h/lojaacheipneus/9263/dc38ebc617b761077c45caef2733bb64.jpeg",
    "marketplace": "magazineluiza",
    "categoria": "",
    "disponivel": true,
    "avaliacoes": 31,
    "nota_media": 8.0,
    "vendedor": "Achei Pneus",
    "frete_gratis": false,
    "parcelamento": "",
    "descricao": "",
    "frete": null
  },
  {
    "titulo": "Pneu Aro 15 Goodyear EfficientGrip Performance 195/55R15 85H",
    "preco": 555.24,
    "link": "https://www.magazineluiza.com.br/pneu-aro-15-goodyear-efficientgrip-performance-195-55r15-85h/p/7515101/au/pine/",
    "data_coleta": "2025-08-08 19:10:27",
    "preco_original": 659.75,
    "promocao": true,
    "imagem": "https://a-static.mlcdn.com.br/280x210/pneu-aro-15-goodyear-efficientgrip-performance-195-55r15-85h/pneustore/10130137/3629cac27779ce6c7af8764746c02944.jpeg",
    "marketplace": "magazineluiza",
    "categoria": "",
    "disponivel": true,
    "avaliacoes": 15,
    "nota_media": 9.0,
    "vendedor": "PneuStore",
    "frete_gratis": false,
    "parcelamento": "",
    "descricao": "",
    "frete": null
  },
  {
    "titulo": "Pneu Goodyear 195/55 R15 85H SL Efficientgrip Performance",
    "preco": 567.63,
    "link": "https://www.magazineluiza.com.br/pneu-goodyear-195-55-r15-85h-sl-efficientgrip-performance/p/ddh0d02875/au/aupa/",
    "data_coleta": "2025-08-08 19:10:33",
    "preco_original": 632.65,
    "promocao": true,
    "imagem": "https://a-static.mlcdn.com.br/280x210/pneu-goodyear-195-55-r15-85h-sl-efficientgrip-performance/pneugreen/1792/37a1f64e2df9213c5cf34cd715847d37.jpeg",
    "marketplace": "magazineluiza",
    "categoria": "",
    "disponivel": true,
    "avaliacoes": 31,
    "nota_media": 8.0,
    "vendedor": "Pneugreen",
    "frete_gratis": false,
    "parcelamento": "",
    "descricao": "",
    "frete": null
  },
  {
    "titulo": "Pneu Goodyear Aro 15 195/55R15 Efficientgrip 85H",
    "preco": 864.49,
    "link": "https://www.magazineluiza.com.br/pneu-goodyear-aro-15-195-55r15-efficientgrip-85h/p/bc00655h64/au/pine/",
    "data_coleta": "2025-08-08 19:10:37",
    "preco_original": 909991275.83,
    "promocao": true,
    "imagem": "https://a-static.mlcdn.com.br/280x210/pneu-goodyear-aro-15-195-55r15-efficientgrip-85h/webpneus/29442/9fb607d444ef3d76ca7e9a4338c34793.jpeg",
    "marketplace": "magazineluiza",
    "categoria": "",
    "disponivel": true,
    "avaliacoes": 2731,
    "nota_media": 8.0,
    "vendedor": "Web Pneus",
    "frete_gratis": false,
    "parcelamento": "",
    "descricao": "",
    "frete": null
  },
  {
    "titulo": "Pneu 195/55R15 Goodyear Efficientgrip Performance 85H",
    "preco": 650.03,
    "link": "https://www.magazineluiza.com.br/pneu-195-55r15-goodyear-efficientgrip-performance-85h/p/efjh76beh4/au/pine/",
    "data_coleta": "2025-08-08 19:10:43",
    "preco_original": 727.18,
    "promocao": true,
    "imagem": "https://a-static.mlcdn.com.br/280x210/pneu-195-55r15-goodyear-efficientgrip-performance-85h/lojaacheipneus/9263/dc38ebc617b761077c45caef2733bb64.jpeg",
    "marketplace": "magazineluiza",
    "categoria": "",
    "disponivel": true,
    "avaliacoes": 31,
    "nota_media": 8.0,
    "vendedor": "Achei Pneus",
    "frete_gratis": false,
    "parcelamento": "",
    "descricao": "",
    "frete": null
  },
  {
    "titulo": "Pneu 195/55R15 Goodyear Efficientgrip Performance 85H",
    "preco": 650.03,
    "link": "https://www.magazineluiza.com.br/pneu-195-55r15-goodyear-efficientgrip-performance-85h/p/efjh76beh4/au/pine/?seller_id=lojaacheipneus",
    "data_coleta": "2025-08-08 19:10:51",
    "preco_original": 727.18,
    "promocao": true,
    "imagem": "https://a-static.mlcdn.com.br/280x210/pneu-195-55r15-goodyear-efficientgrip-performance-85h/lojaacheipneus/9263/dc38ebc617b761077c45caef2733bb64.jpeg",
    "marketplace": "magazineluiza",
    "categoria": "",
    "disponivel": true,
    "avaliacoes": 31,
    "nota_media": 0.0,
    "vendedor": "Achei Pneus",
    "frete_gratis": false,
    "parcelamento": "",
    "descricao": "",
    "frete": null
  },
  {
    "titulo": "Pneu Goodyear Aro 15 195/55R15 Efficientgrip 85H",
    "preco": 864.49,
    "link": "https://www.magazineluiza.com.br/pneu-goodyear-aro-15-195-55r15-efficientgrip-85h/p/bc00655h64/au/pine/?seller_id=webpneus",
    "data_coleta": "2025-08-08 19:10:55",
    "preco_original": 909991275.83,
    "promocao": true,
    "imagem": "https://a-static.mlcdn.com.br/280x210/pneu-goodyear-aro-15-195-55r15-efficientgrip-85h/webpneus/29442/9fb607d444ef3d76ca7e9a4338c34793.jpeg",
    "marketplace": "magazineluiza",
    "categoria": "",
    "disponivel": true,
    "avaliacoes": 2731,
    "nota_media": 0.0,
    "vendedor": "Web Pneus",
    "frete_gratis": false,
    "parcelamento": "",
    "descricao": "",
    "frete": null
  },
  {
    "titulo": "Pneu Goodyear 195/55 R15 85H SL Efficientgrip Performance",
    "preco": 567.63,
    "link": "https://www.magazineluiza.com.br/pneu-goodyear-195-55-r15-85h-sl-efficientgrip-performance/p/ddh0d02875/au/aupa/?seller_id=pneugreen",
    "data_coleta": "2025-08-08 19:10:59",
    "preco_original": 632.65,
    "promocao": true,
    "imagem": "https://a-static.mlcdn.com.br/280x210/pneu-goodyear-195-55-r15-85h-sl-efficientgrip-performance/pneugreen/1792/37a1f64e2df9213c5cf34cd715847d37.jpeg",
    "marketplace": "magazineluiza",
    "categoria": "",
    "disponivel": true,
    "avaliacoes": 31,
    "nota_media": 0.0,
    "vendedor": "Pneugreen",
    "frete_gratis": false,
    "parcelamento": "",
    "descricao": "",
    "frete": null
  },
  {
    "titulo": "Pneu Aro 15 Goodyear EfficientGrip Performance 195/55R15 85H",
    "preco": 555.24,
    "link": "https://www.magazineluiza.com.br/pneu-aro-15-goodyear-efficientgrip-performance-195-55r15-85h/p/751510100/au/pine/?seller_id=pneustore",
    "data_coleta": "2025-08-08 19:11:04",
    "preco_original": 659.75,
    "promocao": true,
    "imagem": "https://a-static.mlcdn.com.br/280x210/pneu-aro-15-goodyear-efficientgrip-performance-195-55r15-85h/pneustore/10130137/3629cac27779ce6c7af8764746c02944.jpeg",
    "marketplace": "magazineluiza",
    "categoria": "",
    "disponivel": true,
    "avaliacoes": 15,
    "nota_media": 0.0,
    "vendedor": "PneuStore",
    "frete_gratis": false,
    "parcelamento": "",
    "descricao": "",
    "frete": null
  },
  {
    "titulo": "Pneu Aro 15 Goodyear EfficientGrip Performance 195/55R15 85H",
    "preco": 555.24,
    "link": "https://www.magazineluiza.com.br/pneu-aro-15-goodyear-efficientgrip-performance-195-55r15-85h/p/751510100/au/pine/?seller_id=pneustore",
    "data_coleta": "2025-08-08 19:11:09",
    "preco_original": 659.75,
    "promocao": true,
    "imagem": "https://a-static.mlcdn.com.br/280x210/pneu-aro-15-goodyear-efficientgrip-performance-195-55r15-85h/pneustore/10130137/3629cac27779ce6c7af8764746c02944.jpeg",
    "marketplace": "magazineluiza",
    "categoria": "",
    "disponivel": true,
    "avaliacoes": 15,
    "nota_media": 0.0,
    "vendedor": "PneuStore",
    "frete_gratis": false,
    "parcelamento": "",
    "descricao": "",
    "frete": null
  },
  {
    "titulo": "Pneu Goodyear 195/55 R15 85H SL Efficientgrip Performance",
    "preco": 567.63,
    "link": "https://www.magazineluiza.com.br/pneu-goodyear-195-55-r15-85h-sl-efficientgrip-performance/p/ddh0d02875/au/aupa/?seller_id=pneugreen",
    "data_coleta": "2025-08-08 19:11:15",
    "preco_original": 632.65,
    "promocao": true,
    "imagem": "https://a-static.mlcdn.com.br/280x210/pneu-goodyear-195-55-r15-85h-sl-efficientgrip-performance/pneugreen/1792/37a1f64e2df9213c5cf34cd715847d37.jpeg",
    "marketplace": "magazineluiza",
    "categoria": "",
    "disponivel": true,
    "avaliacoes": 31,
    "nota_media": 0.0,
    "vendedor": "Pneugreen",
    "frete_gratis": false,
    "parcelamento": "",
    "descricao": "",
    "frete": null
  },
  {
    "titulo": "Pneu Aro 15 Goodyear EfficientGrip Performance 195/55R15 85H",
    "preco": 555.24,
    "link": "https://www.magazineluiza.com.br/pneu-aro-15-goodyear-efficientgrip-performance-195-55r15-85h/p/7515101/au/pine/",
    "data_coleta": "2025-08-08 19:11:35",
    "preco_original": 659.75,
    "promocao": true,
    "imagem": "https://a-static.mlcdn.com.br/280x210/pneu-aro-15-goodyear-efficientgrip-performance-195-55r15-85h/pneustore/10130137/3629cac27779ce6c7af8764746c02944.jpeg",
    "marketplace": "magazineluiza",
    "categoria": "",
    "disponivel": true,
    "avaliacoes": 15,
    "nota_media": 9.0,
    "vendedor": "PneuStore",
    "frete_gratis": false,
    "parcelamento": "",
    "descricao": "",
    "frete": null
  },
  {
    "titulo": "Pneu Goodyear 195/55 R15 85H SL Efficientgrip Performance",
    "preco": 567.63,
    "link": "https://www.magazineluiza.com.br/pneu-goodyear-195-55-r15-85h-sl-efficientgrip-performance/p/ddh0d02875/au/aupa/",
    "data_coleta": "2025-08-08 19:11:40",
    "preco_original": 632.65,
    "promocao": true,
    "imagem": "https://a-static.mlcdn.com.br/280x210/pneu-goodyear-195-55-r15-85h-sl-efficientgrip-performance/pneugreen/1792/37a1f64e2df9213c5cf34cd715847d37.jpeg",
    "marketplace": "magazineluiza",
    "categoria": "",
    "disponivel": true,
    "avaliacoes": 31,
    "nota_media": 8.0,
    "vendedor": "Pneugreen",
    "frete_gratis": false,
    "parcelamento": "",
    "descricao": "",
    "frete": null
  },
  {
    "titulo": "Pneu Goodyear Aro 15 195/55R15 Efficientgrip 85H",
    "preco": 864.49,
    "link": "https://www.magazineluiza.com.br/pneu-goodyear-aro-15-195-55r15-efficientgrip-85h/p/bc00655h64/au/pine/",
    "data_coleta": "2025-08-08 19:11:44",
    "preco_original": 909991275.83,
    "promocao": true,
    "imagem": "https://a-static.mlcdn.com.br/280x210/pneu-goodyear-aro-15-195-55r15-efficientgrip-85h/webpneus/29442/9fb607d444ef3d76ca7e9a4338c34793.jpeg",
    "marketplace": "magazineluiza",
    "categoria": "",
    "disponivel": true,
    "avaliacoes": 2731,
    "nota_media": 8.0,
    "vendedor": "Web Pneus",
    "frete_gratis": false,
    "parcelamento": "",
    "descricao": "",
    "frete": null
  },
  {
    "titulo": "Pneu 195/55R15 Goodyear Efficientgrip Performance 85H",
    "preco": 650.03,
    "link": "https://www.magazineluiza.com.br/pneu-195-55r15-goodyear-efficientgrip-performance-85h/p/efjh76beh4/au/pine/",
    "data_coleta": "2025-08-08 19:11:49",
    "preco_original": 727.18,
    "promocao": true,
    "imagem": "https://a-static.mlcdn.com.br/280x210/pneu-195-55r15-goodyear-efficientgrip-performance-85h/lojaacheipneus/9263/dc38ebc617b761077c45caef2733bb64.jpeg",
    "marketplace": "magazineluiza",
    "categoria": "",
    "disponivel": true,
    "avaliacoes": 31,
    "nota_media": 8.0,
    "vendedor": "Achei Pneus",
    "frete_gratis": false,
    "parcelamento": "",
    "descricao": "",
    "frete": null
  },
  {
    "titulo": "Pneu Goodyear 195/55 R15 85H SL Efficientgrip Performance",
    "preco": 567.63,
    "link": "https://www.magazineluiza.com.br/pneu-goodyear-195-55-r15-85h-sl-efficientgrip-performance/p/ddh0d02875/au/aupa/?seller_id=pneugreen",
    "data_coleta": "2025-08-08 19:11:59",
    "preco_original": 632.65,
    "promocao": true,
    "imagem": "https://a-static.mlcdn.com.br/280x210/pneu-goodyear-195-55-r15-85h-sl-efficientgrip-performance/pneugreen/1792/37a1f64e2df9213c5cf34cd715847d37.jpeg",
    "marketplace": "magazineluiza",
    "categoria": "",
    "disponivel": true,
    "avaliacoes": 31,
    "nota_media": 0.0,
    "vendedor": "Pneugreen",
    "frete_gratis": false,
    "parcelamento": "",
    "descricao": "",
    "frete": null
  },
  {
    "titulo": "Pneu Aro 15 Goodyear EfficientGrip Performance 195/55R15 85H",
    "preco": 555.24,
    "link": "https://www.magazineluiza.com.br/pneu-aro-15-goodyear-efficientgrip-performance-195-55r15-85h/p/751510100/au/pine/?seller_id=pneustore",
    "data_coleta": "2025-08-08 19:12:02",
    "preco_original": 659.75,
    "promocao": true,
    "imagem": "https://a-static.mlcdn.com.br/280x210/pneu-aro-15-goodyear-efficientgrip-performance-195-55r15-85h/pneustore/10130137/3629cac27779ce6c7af8764746c02944.jpeg",
    "marketplace": "magazineluiza",
    "categoria": "",
    "disponivel": true,
    "avaliacoes": 15,
    "nota_media": 0.0,
    "vendedor": "PneuStore",
    "frete_gratis": false,
    "parcelamento": "",
    "descricao": "",
    "frete": null
  },
  {
    "titulo": "Pneu Goodyear Aro 15 195/55R15 Efficientgrip 85H",
    "preco": 864.49,
    "link": "https://www.magazineluiza.com.br/pneu-goodyear-aro-15-195-55r15-efficientgrip-85h/p/bc00655h64/au/pine/?seller_id=webpneus",
    "data_coleta": "2025-08-08 19:12:06",
    "preco_original": 909991275.83,
    "promocao": true,
    "imagem": "https://a-static.mlcdn.com.br/280x210/pneu-goodyear-aro-15-195-55r15-efficientgrip-85h/webpneus/29442/9fb607d444ef3d76ca7e9a4338c34793.jpeg",
    "marketplace": "magazineluiza",
    "categoria": "",
    "disponivel": true,
    "avaliacoes": 2731,
    "nota_media": 0.0,
    "vendedor": "Web Pneus",
    "frete_gratis": false,
    "parcelamento": "",
    "descricao": "",
    "frete": null
  },
  {
    "titulo": "Pneu 195/55R15 Goodyear Efficientgrip Performance 85H",
    "preco": 650.03,
    "link": "https://www.magazineluiza.com.br/pneu-195-55r15-goodyear-efficientgrip-performance-85h/p/efjh76beh4/au/pine/?seller_id=lojaacheipneus",
    "data_coleta": "2025-08-08 19:12:11",
    "preco_original": 727.18,
    "promocao": true,
    "imagem": "https://a-static.mlcdn.com.br/280x210/pneu-195-55r15-goodyear-efficientgrip-performance-85h/lojaacheipneus/9263/dc38ebc617b761077c45caef2733bb64.jpeg",
    "marketplace": "magazineluiza",
    "categoria": "",
    "disponivel": true,
    "avaliacoes": 31,
    "nota_media": 0.0,
    "vendedor": "Achei Pneus",
    "frete_gratis": false,
    "parcelamento": "",
    "descricao": "",
    "frete": null
  },
  {
    "titulo": "Pneu Aro 15 Goodyear EfficientGrip Performance 195/55R15 85H",
    "preco": 555.24,
    "link": "https://www.magazineluiza.com.br/pneu-aro-15-goodyear-efficientgrip-performance-195-55r15-85h/p/751510100/au/pine/?seller_id=pneustore",
    "data_coleta": "2025-08-08 19:12:18",
    "preco_original": 659.75,
    "promocao": true,
    "imagem": "https://a-static.mlcdn.com.br/280x210/pneu-aro-15-goodyear-efficientgrip-performance-195-55r15-85h/pneustore/10130137/3629cac27779ce6c7af8764746c02944.jpeg",
    "marketplace": "magazineluiza",
    "categoria": "",
    "disponivel": true,
    "avaliacoes": 15,
    "nota_media": 0.0,
    "vendedor": "PneuStore",
    "frete_gratis": false,
    "parcelamento": "",
    "descricao": "",
    "frete": null
  }
]