[
  {
    "titulo": "Pneu 185/70R14 Continental PowerContact 2 88H Aro 14",
    "link": "https://www.mercadolivre.com.br/pneu-18570r14-continental-powercontact-2-88h-aro-14/p/MLB16027559",
    "preco": 507.21,
    "brand": "continental",
    "model": "powercontact",
    "size": "",
    "query_strict": "pneu 185/70R14 Continental PowerContact",
    "size_norm": "185-70-r14",
    "brand_expected": "continental",
    "line_expected": "powercontact",
    "size_ok": true,
    "free_ship": true,
    "frete": 0.0,
    "local": "",
    "vendedor": "",
    "condicao": "Novo",
    "frete_gratis": true,
    "marketplace": "mercadolivre",
    "marca": "continental",
    "data_coleta": "2025-08-11 17:17:48",
    "preco_original": null,
    "preco_desconto": 507.21,
    "desconto_pct": null,
    "shipping": {}
  },
  {
    "titulo": "Pneu 185/70R14 Continental PowerContact 2 88H Aro 14",
    "link": "https://click1.mercadolivre.com.br/mclics/clicks/external/MLB/count?a=l%2BNby8xDyylAOS3lCp86IV1tf96pFgn8k%2Fy1lSnPhs7jlTG3wgVoVTgSeujH6WgKiZgzK%2BHaLYaJ8RC%2FtCZcmSZCud9W%2B7yx6Wq7rKOQZVDLx7MmQUM69Q9Jkc8gAg%2BXnM06pHPJ%2B0NVsSsdNPzbofLX1ujGUY%2BfvSeC89VgCHk0gqvNkXodc949aPCaBd842gql2vMBD0LDlC9h4OsnJwcD%2BN2vlMnusfhnG8qtFlJt8y%2BpstEbW8s0RrUxXvdExR%2Fv6tH%2BxWj2NaRuRVZTMvMTYEyPWwCZfrRkcopv9CycJ6lpY6qPLRbOuZ8o%2F3RWZYXRv9rHvttTIM3F%2FyLvdirgz3XaNENxjgK7B%2BKOJJ8opPKA2wtwNq9MySz6o4Rlsf8BXtAeW6tLp9dUEmdvIXLXkzPleqpAbv5%2FmFmst0J18DrNR6Vpz7rGM8aWhIWsQ7A4EQPSxj5qaaZRkv66Y01wokIvN8EHwZBlYtO24vkttGNajvYCl9LHDwCKK7TWqYidLk0x3eE5a6wOGySNDf0bRXEXPy16pxz1GgajT0Zm3daj0w9u%2BBQetiIhcBAz9Qls3SHpPTZLFxdCVcSyzh%2F%2B30tNnhK%2FNFZ%2F6iDbxPtuwMLJALkBoR8eG5M4ku8lCxzEiVPjvwi0UOJ6P6lwYLPb8LDAIodm2q1PB42yvuHVTOhM%2BL%2Ffd880rTxu9NsbxnV%2FI7SDHewvA8poELmn4Q409rtk5SrzMS3HGe5tDX8d2CCXWEjLWvOvqL5xYn4OmQCNn2YSnV%2Fw%2FwOA96TClPm07CXnqiIWWy6i61O1UzDrvbs8zlM%2BP8%2BCT58sr877%2BcxtxAy%2Fz%2FvF2pkMtA7mPLb8CrBfRuHqVRe%2FkpcqgrN66m8EHKxcDUm7Xgksga6luq0JtFNVrwB%2FcfX7tL7q0JD%2Fua8TyTark2TY8P3E5egybrC5P3%2FzfdOzIdVMFebPhkq%2Fzl0hvRVla1F4cfCWfBUupgyp3MvwPVHb",
    "preco": 507.21,
    "brand": "continental",
    "model": "powercontact",
    "size": "",
    "query_strict": "pneu 185/70R14 Continental PowerContact",
    "size_norm": "185-70-r14",
    "brand_expected": "continental",
    "line_expected": "powercontact",
    "size_ok": true,
    "free_ship": true,
    "frete": 0.0,
    "local": "",
    "vendedor": "",
    "condicao": "Novo",
    "frete_gratis": true,
    "marketplace": "mercadolivre",
    "marca": "continental",
    "data_coleta": "2025-08-11 17:17:50",
    "preco_original": null,
    "preco_desconto": 507.21,
    "desconto_pct": null,
    "shipping": {}
  },
  {
    "titulo": "Pneu Continental Urbano Contipowercontact 185/70r14 88 (560kg)",
    "link": "https://www.mercadolivre.com.br/pneu-continental-urbano-contipowercontact-18570r14-88-560kg/p/MLB34226466",
    "preco": 944.52,
    "brand": "continental",
    "model": "powercontact",
    "size": "",
    "query_strict": "pneu 185/70R14 Continental PowerContact",
    "size_norm": "185-70-r14",
    "brand_expected": "continental",
    "line_expected": "powercontact",
    "size_ok": true,
    "free_ship": true,
    "frete": 0.0,
    "local": "",
    "vendedor": "",
    "condicao": "Novo",
    "frete_gratis": true,
    "marketplace": "mercadolivre",
    "marca": "continental",
    "data_coleta": "2025-08-11 17:17:51",
    "preco_original": null,
    "preco_desconto": 944.52,
    "desconto_pct": null,
    "shipping": {}
  },
  {
    "titulo": "Pneu 185/70r14 Continental Powercontact 2 88h",
    "link": "https://produto.mercadolivre.com.br/MLB-1207258704-pneu-18570r14-continental-powercontact-2-88h-_JM",
    "preco": 566.0,
    "brand": "continental",
    "model": "powercontact",
    "size": "",
    "query_strict": "pneu 185/70R14 Continental PowerContact",
    "size_norm": "185-70-r14",
    "brand_expected": "continental",
    "line_expected": "powercontact",
    "size_ok": true,
    "free_ship": true,
    "frete": 0.0,
    "local": "",
    "vendedor": "",
    "condicao": "Novo",
    "frete_gratis": true,
    "marketplace": "mercadolivre",
    "marca": "continental",
    "data_coleta": "2025-08-11 17:17:53",
    "preco_original": null,
    "preco_desconto": 566.0,
    "desconto_pct": null,
    "shipping": {}
  },
  {
    "titulo": "Pneu Continental 185/70 R14 88 H Contipowercontact",
    "link": "https://produto.mercadolivre.com.br/MLB-2185802260-pneu-continental-18570-r14-88-h-contipowercontact-_JM",
    "preco": 944.52,
    "brand": "continental",
    "model": "powercontact",
    "size": "",
    "query_strict": "pneu 185/70R14 Continental PowerContact",
    "size_norm": "185-70-r14",
    "brand_expected": "continental",
    "line_expected": "powercontact",
    "size_ok": true,
    "free_ship": true,
    "frete": 0.0,
    "local": "",
    "vendedor": "",
    "condicao": "Novo",
    "frete_gratis": true,
    "marketplace": "mercadolivre",
    "marca": "continental",
    "data_coleta": "2025-08-11 17:17:55",
    "preco_original": null,
    "preco_desconto": 944.52,
    "desconto_pct": null,
    "shipping": {}
  },
  {
    "titulo": "Pneu Continental Aro 14 185/70r14 Powercontact 2 88h Onix",
    "link": "https://produto.mercadolivre.com.br/MLB-3829330043-pneu-continental-aro-14-18570r14-powercontact-2-88h-onix-_JM",
    "preco": 577.5,
    "brand": "continental",
    "model": "powercontact",
    "size": "",
    "query_strict": "pneu 185/70R14 Continental PowerContact",
    "size_norm": "185-70-r14",
    "brand_expected": "continental",
    "line_expected": "powercontact",
    "size_ok": true,
    "free_ship": true,
    "frete": 0.0,
    "local": "",
    "vendedor": "",
    "condicao": "Novo",
    "frete_gratis": true,
    "marketplace": "mercadolivre",
    "marca": "continental",
    "data_coleta": "2025-08-11 17:17:57",
    "preco_original": null,
    "preco_desconto": 577.5,
    "desconto_pct": null,
    "shipping": {}
  },
  {
    "titulo": "Pneu Continental Aro 14 185/70r14 Powercontact 2 88h Onix",
    "link": "https://produto.mercadolivre.com.br/MLB-4008759135-pneu-continental-aro-14-18570r14-powercontact-2-88h-onix-_JM",
    "preco": 627.94,
    "brand": "continental",
    "model": "powercontact",
    "size": "",
    "query_strict": "pneu 185/70R14 Continental PowerContact",
    "size_norm": "185-70-r14",
    "brand_expected": "continental",
    "line_expected": "powercontact",
    "size_ok": true,
    "free_ship": true,
    "frete": 0.0,
    "local": "",
    "vendedor": "",
    "condicao": "Novo",
    "frete_gratis": true,
    "marketplace": "mercadolivre",
    "marca": "continental",
    "data_coleta": "2025-08-11 17:17:59",
    "preco_original": null,
    "preco_desconto": 627.94,
    "desconto_pct": null,
    "shipping": {}
  },
  {
    "titulo": "Pneu Continental Aro 14 Powercontact 2 185/70r14 88h Índice De Velocidade H",
    "link": "https://www.mercadolivre.com.br/pneu-continental-aro-14-powercontact-2-18570r14-88h-indice-de-velocidade-h/p/MLB34699133",
    "preco": 577.02,
    "brand": "continental",
    "model": "powercontact",
    "size": "",
    "query_strict": "pneu 185/70R14 Continental PowerContact",
    "size_norm": "185-70-r14",
    "brand_expected": "continental",
    "line_expected": "powercontact",
    "size_ok": true,
    "free_ship": true,
    "frete": 0.0,
    "local": "",
    "vendedor": "",
    "condicao": "Novo",
    "frete_gratis": true,
    "marketplace": "mercadolivre",
    "marca": "continental",
    "data_coleta": "2025-08-11 17:18:01",
    "preco_original": null,
    "preco_desconto": 577.02,
    "desconto_pct": null,
    "shipping": {}
  },
  {
    "titulo": "Pneu Continental Aro 14 Powercontact 2 185/70r14 88h",
    "link": "https://produto.mercadolivre.com.br/MLB-3949676873-pneu-continental-aro-14-powercontact-2-18570r14-88h-_JM?searchVariation=186703479453",
    "preco": 616.74,
    "brand": "continental",
    "model": "powercontact",
    "size": "",
    "query_strict": "pneu 185/70R14 Continental PowerContact",
    "size_norm": "185-70-r14",
    "brand_expected": "continental",
    "line_expected": "powercontact",
    "size_ok": true,
    "free_ship": true,
    "frete": 0.0,
    "local": "",
    "vendedor": "",
    "condicao": "Novo",
    "frete_gratis": true,
    "marketplace": "mercadolivre",
    "marca": "continental",
    "data_coleta": "2025-08-11 17:18:03",
    "preco_original": null,
    "preco_desconto": 616.74,
    "desconto_pct": null,
    "shipping": {}
  },
  {
    "titulo": "Pneu Continental Aro 14 Powercontact 2 185/70r14 88h",
    "link": "https://produto.mercadolivre.com.br/MLB-5254698238-pneu-continental-aro-14-powercontact-2-18570r14-88h-_JM?searchVariation=186724351051",
    "preco": 616.74,
    "brand": "continental",
    "model": "powercontact",
    "size": "",
    "query_strict": "pneu 185/70R14 Continental PowerContact",
    "size_norm": "185-70-r14",
    "brand_expected": "continental",
    "line_expected": "powercontact",
    "size_ok": true,
    "free_ship": true,
    "frete": 0.0,
    "local": "",
    "vendedor": "",
    "condicao": "Novo",
    "frete_gratis": true,
    "marketplace": "mercadolivre",
    "marca": "continental",
    "data_coleta": "2025-08-11 17:18:04",
    "preco_original": null,
    "preco_desconto": 616.74,
    "desconto_pct": null,
    "shipping": {}
  },
  {
    "titulo": "Pneu Continental Aro 14 Powercontact 2 185/70r14 88h",
    "link": "https://produto.mercadolivre.com.br/MLB-5255348372-pneu-continental-aro-14-powercontact-2-18570r14-88h-_JM?searchVariation=182761065028",
    "preco": 577.02,
    "brand": "continental",
    "model": "powercontact",
    "size": "",
    "query_strict": "pneu 185/70R14 Continental PowerContact",
    "size_norm": "185-70-r14",
    "brand_expected": "continental",
    "line_expected": "powercontact",
    "size_ok": true,
    "free_ship": true,
    "frete": 0.0,
    "local": "",
    "vendedor": "",
    "condicao": "Novo",
    "frete_gratis": true,
    "marketplace": "mercadolivre",
    "marca": "continental",
    "data_coleta": "2025-08-11 17:18:06",
    "preco_original": null,
    "preco_desconto": 577.02,
    "desconto_pct": null,
    "shipping": {}
  },
  {
    "titulo": "Pneu 185/70r14 Continental Powercontact 2 88h Aro 14",
    "link": "https://produto.mercadolivre.com.br/MLB-5424051026-pneu-18570r14-continental-powercontact-2-88h-aro-14-_JM?searchVariation=188322839745",
    "preco": 591.7,
    "brand": "continental",
    "model": "powercontact",
    "size": "",
    "query_strict": "pneu 185/70R14 Continental PowerContact",
    "size_norm": "185-70-r14",
    "brand_expected": "continental",
    "line_expected": "powercontact",
    "size_ok": true,
    "free_ship": true,
    "frete": 0.0,
    "local": "",
    "vendedor": "",
    "condicao": "Novo",
    "frete_gratis": true,
    "marketplace": "mercadolivre",
    "marca": "continental",
    "data_coleta": "2025-08-11 17:18:07",
    "preco_original": null,
    "preco_desconto": 591.7,
    "desconto_pct": null,
    "shipping": {}
  },
  {
    "titulo": "Pneu 185/70r14 Continental Powercontact 2 88h",
    "link": "https://produto.mercadolivre.com.br/MLB-1166105246-pneu-18570r14-continental-powercontact-2-88h-_JM",
    "preco": 609.0,
    "brand": "continental",
    "model": "powercontact",
    "size": "",
    "query_strict": "pneu 185/70R14 Continental PowerContact",
    "size_norm": "185-70-r14",
    "brand_expected": "continental",
    "line_expected": "powercontact",
    "size_ok": true,
    "free_ship": true,
    "frete": 0.0,
    "local": "",
    "vendedor": "",
    "condicao": "Novo",
    "frete_gratis": true,
    "marketplace": "mercadolivre",
    "marca": "continental",
    "data_coleta": "2025-08-11 17:18:09",
    "preco_original": null,
    "preco_desconto": 609.0,
    "desconto_pct": null,
    "shipping": {}
  },
  {
    "titulo": "Pneu Aro 14 Continental 185 70 R14 88t Contipowercontact T",
    "link": "https://www.mercadolivre.com.br/pneu-aro-14-continental-185-70-r14-88t-contipowercontact/up/MLBU3025597841",
    "preco": 741.85,
    "brand": "continental",
    "model": "powercontact",
    "size": "",
    "query_strict": "pneu 185/70R14 Continental PowerContact",
    "size_norm": "185-70-r14",
    "brand_expected": "continental",
    "line_expected": "powercontact",
    "size_ok": true,
    "free_ship": true,
    "frete": 0.0,
    "local": "",
    "vendedor": "",
    "condicao": "Novo",
    "frete_gratis": true,
    "marketplace": "mercadolivre",
    "marca": "continental",
    "data_coleta": "2025-08-11 17:18:10",
    "preco_original": null,
    "preco_desconto": 741.85,
    "desconto_pct": null,
    "shipping": {}
  },
  {
    "titulo": "Pneu Continental Powercontact 2 185/70 R14 88h",
    "link": "https://produto.mercadolivre.com.br/MLB-1886897937-pneu-continental-powercontact-2-18570-r14-88h-_JM?searchVariation=84952633726",
    "preco": 551.71,
    "brand": "continental",
    "model": "powercontact",
    "size": "",
    "query_strict": "pneu 185/70R14 Continental PowerContact",
    "size_norm": "185-70-r14",
    "brand_expected": "continental",
    "line_expected": "powercontact",
    "size_ok": true,
    "free_ship": true,
    "frete": 0.0,
    "local": "",
    "vendedor": "",
    "condicao": "Novo",
    "frete_gratis": true,
    "marketplace": "mercadolivre",
    "marca": "continental",
    "data_coleta": "2025-08-11 17:18:12",
    "preco_original": null,
    "preco_desconto": 551.71,
    "desconto_pct": null,
    "shipping": {}
  },
  {
    "titulo": "Pneu Continental Aro 14 185/70r14 Powercontact 2 88h Onix",
    "link": "https://produto.mercadolivre.com.br/MLB-2189072343-pneu-continental-aro-14-18570r14-powercontact-2-88h-onix-_JM",
    "preco": 614.59,
    "brand": "continental",
    "model": "powercontact",
    "size": "",
    "query_strict": "pneu 185/70R14 Continental PowerContact",
    "size_norm": "185-70-r14",
    "brand_expected": "continental",
    "line_expected": "powercontact",
    "size_ok": true,
    "free_ship": true,
    "frete": 0.0,
    "local": "",
    "vendedor": "",
    "condicao": "Novo",
    "frete_gratis": true,
    "marketplace": "mercadolivre",
    "marca": "continental",
    "data_coleta": "2025-08-11 17:18:14",
    "preco_original": null,
    "preco_desconto": 614.59,
    "desconto_pct": null,
    "shipping": {}
  },
  {
    "titulo": "Pneu Continental Aro 14 Powercontact 2 185/70r14 88h",
    "link": "https://produto.mercadolivre.com.br/MLB-3951189267-pneu-continental-aro-14-powercontact-2-18570r14-88h-_JM?searchVariation=186725784391",
    "preco": 616.74,
    "brand": "continental",
    "model": "powercontact",
    "size": "",
    "query_strict": "pneu 185/70R14 Continental PowerContact",
    "size_norm": "185-70-r14",
    "brand_expected": "continental",
    "line_expected": "powercontact",
    "size_ok": true,
    "free_ship": true,
    "frete": 0.0,
    "local": "",
    "vendedor": "",
    "condicao": "Novo",
    "frete_gratis": true,
    "marketplace": "mercadolivre",
    "marca": "continental",
    "data_coleta": "2025-08-11 17:18:16",
    "preco_original": null,
    "preco_desconto": 616.74,
    "desconto_pct": null,
    "shipping": {}
  },
  {
    "titulo": "Pneu Continental 185/70r14 Contipowercontact 2 88h - Ls E Lt T",
    "link": "https://www.mercadolivre.com.br/pneu-continental-18570r14-contipowercontact-2-88h--ls-e-lt/up/MLBU1407508036",
    "preco": 525.59,
    "brand": "continental",
    "model": "powercontact",
    "size": "",
    "query_strict": "pneu 185/70R14 Continental PowerContact",
    "size_norm": "185-70-r14",
    "brand_expected": "continental",
    "line_expected": "powercontact",
    "size_ok": true,
    "free_ship": true,
    "frete": 0.0,
    "local": "",
    "vendedor": "",
    "condicao": "Novo",
    "frete_gratis": true,
    "marketplace": "mercadolivre",
    "marca": "continental",
    "data_coleta": "2025-08-11 17:18:17",
    "preco_original": null,
    "preco_desconto": 525.59,
    "desconto_pct": null,
    "shipping": {}
  },
  {
    "titulo": "Pneu Continental Aro 14 185/70r14 88h Powercontact 2 H",
    "link": "https://www.mercadolivre.com.br/pneu-continental-aro-14-18570r14-88h-powercontact-2/up/MLBU1406773788",
    "preco": 590.9,
    "brand": "continental",
    "model": "powercontact",
    "size": "",
    "query_strict": "pneu 185/70R14 Continental PowerContact",
    "size_norm": "185-70-r14",
    "brand_expected": "continental",
    "line_expected": "powercontact",
    "size_ok": true,
    "free_ship": true,
    "frete": 0.0,
    "local": "",
    "vendedor": "",
    "condicao": "Novo",
    "frete_gratis": true,
    "marketplace": "mercadolivre",
    "marca": "continental",
    "data_coleta": "2025-08-11 17:18:18",
    "preco_original": null,
    "preco_desconto": 590.9,
    "desconto_pct": null,
    "shipping": {}
  },
  {
    "titulo": "Pneu Continental Powercontact 2 185/70r14 88h - Ht H",
    "link": "https://www.mercadolivre.com.br/pneu-continental-powercontact-2-18570r14-88h--ht/up/MLBU1596632425",
    "preco": 566.64,
    "brand": "continental",
    "model": "powercontact",
    "size": "",
    "query_strict": "pneu 185/70R14 Continental PowerContact",
    "size_norm": "185-70-r14",
    "brand_expected": "continental",
    "line_expected": "powercontact",
    "size_ok": true,
    "free_ship": true,
    "frete": 0.0,
    "local": "",
    "vendedor": "",
    "condicao": "Novo",
    "frete_gratis": true,
    "marketplace": "mercadolivre",
    "marca": "continental",
    "data_coleta": "2025-08-11 17:18:20",
    "preco_original": null,
    "preco_desconto": 566.64,
    "desconto_pct": null,
    "shipping": {}
  },
  {
    "titulo": "Pneu Aro 14 Continental 185 70 R14 88t Contipowercontact T",
    "link": "https://www.mercadolivre.com.br/pneu-aro-14-continental-185-70-r14-88t-contipowercontact/up/MLBU2728182948",
    "preco": 715.13,
    "brand": "continental",
    "model": "powercontact",
    "size": "",
    "query_strict": "pneu 185/70R14 Continental PowerContact",
    "size_norm": "185-70-r14",
    "brand_expected": "continental",
    "line_expected": "powercontact",
    "size_ok": true,
    "free_ship": true,
    "frete": 0.0,
    "local": "",
    "vendedor": "",
    "condicao": "Novo",
    "frete_gratis": true,
    "marketplace": "mercadolivre",
    "marca": "continental",
    "data_coleta": "2025-08-11 17:18:22",
    "preco_original": null,
    "preco_desconto": 715.13,
    "desconto_pct": null,
    "shipping": {}
  },
  {
    "titulo": "Pneu Continental Aro 14 Powercontact 2 185/70r14 88h",
    "link": "https://www.mercadolivre.com.br/pneu-continental-aro-14-powercontact-2-18570r14-88h/p/MLB34697783",
    "preco": 763.0,
    "brand": "continental",
    "model": "powercontact",
    "size": "",
    "query_strict": "pneu 185/70R14 Continental PowerContact",
    "size_norm": "185-70-r14",
    "brand_expected": "continental",
    "line_expected": "powercontact",
    "size_ok": true,
    "free_ship": true,
    "frete": 0.0,
    "local": "",
    "vendedor": "",
    "condicao": "Novo",
    "frete_gratis": true,
    "marketplace": "mercadolivre",
    "marca": "continental",
    "data_coleta": "2025-08-11 17:18:24",
    "preco_original": null,
    "preco_desconto": 763.0,
    "desconto_pct": null,
    "shipping": {}
  },
  {
    "titulo": "Pneu Continental Powercontact 2 185/70r14 88h Ht",
    "link": "https://produto.mercadolivre.com.br/MLB-900055956-pneu-continental-powercontact-2-18570r14-88h-ht-_JM?searchVariation=182356904781",
    "preco": 609.82,
    "brand": "continental",
    "model": "powercontact",
    "size": "",
    "query_strict": "pneu 185/70R14 Continental PowerContact",
    "size_norm": "185-70-r14",
    "brand_expected": "continental",
    "line_expected": "powercontact",
    "size_ok": true,
    "free_ship": true,
    "frete": 0.0,
    "local": "",
    "vendedor": "",
    "condicao": "Novo",
    "frete_gratis": true,
    "marketplace": "mercadolivre",
    "marca": "continental",
    "data_coleta": "2025-08-11 17:19:56",
    "preco_original": null,
    "preco_desconto": 609.82,
    "desconto_pct": null,
    "shipping": {}
  },
  {
    "titulo": "Pneu Continental Aro 14 185/70r14 Powercontact 2 88h",
    "link": "https://www.mercadolivre.com.br/pneu-continental-aro-14-18570r14-powercontact-2-88h/up/MLBU1757078348",
    "preco": 816.8,
    "brand": "continental",
    "model": "powercontact",
    "size": "",
    "query_strict": "pneu 185/70R14 Continental PowerContact",
    "size_norm": "185-70-r14",
    "brand_expected": "continental",
    "line_expected": "powercontact",
    "size_ok": true,
    "free_ship": true,
    "frete": 0.0,
    "local": "",
    "vendedor": "",
    "condicao": "Novo",
    "frete_gratis": true,
    "marketplace": "mercadolivre",
    "marca": "continental",
    "data_coleta": "2025-08-11 17:19:57",
    "preco_original": null,
    "preco_desconto": 816.8,
    "desconto_pct": null,
    "shipping": {}
  },
  {
    "titulo": "Pneu 185/70R14 Continental PowerContact 2 88H Aro 14",
    "link": "https://click1.mercadolivre.com.br/mclics/clicks/external/MLB/count?a=l3J6ARjnu9vhnSeZvoVKVGgJ98bhPdjBBrAQSwZTZ7kcCy2GyIdus1Jhf%2Bq5u0EAy7gzSxPaN52jqDWig7hd2cMjCrTJNIjC2nhMQzWZeQQoMVIVVD%2FSUM67vNwB%2B0m7tasWYLOn8%2BrMpbphFGPJyb%2FsqhhDGwioblMkhMRwrbH%2BmINve1tS459Xf3DRBEI3yVtJfe5aiDnibifmn65KuFj6ttNFdQWEqQp5upE9J6vBiEGJaAiLvYGu3mBuLwRX4p7e0MLCsGc39KLMi01LSIsj9CClH7tdeAXqqKLQKL5pggqgTPm7fniH0WLHLLF02kFsKCpVfDSfrXAihAlKAMhgSM7%2BLVhKwQ1wU%2Beatrx4c1DT4MIWF2L5fOq7%2F9U3%2BBJ%2F%2FwhVHtzHZln%2BNLIYnkWr7vfHOw8dtLukmgHkTKDU189rVoZu6JYAHJof1JJJzT9%2F0pmalycXanja%2F85JKIpoKytoyZwV2Ph%2B0HDf3%2FVB8BS7f018MzFkfvbh4YO4R1AeBQFS7bNoM9sen%2FtKsCle6%2FZsa1hIj1mXpxQp2jg5aheuIIcsT371YzGFkgFf6KRBNTlZEw3CuC4ch0%2FP8Mc8mF3mzbXU%2F%2BcJ%2B4YQe%2FNzGbaxWIxSVex9GXZRGgawUZ%2BzXNk3svgYFNfB2IX1UkT%2FKpVqiqyTG4zgquzp3uAUE6r5U0LVX1YCTaIYxXCXxVbwZT4mO7yS8%2FITvjicoUHtT3ZRMdsygH5J4D67jYHUTAck4aUBJbmQHWXLSsTVt7d2G9vvB2YdxyHuQk3e9szmmOo4H1KZW7tfxP8xlOMb87RJQisLvqXOhUq45e%2FXNEtb%2FFu2JxON9roPZK%2FEHrpVPqKABGfvtwXfgpO7FXFCbZrr1vvmw5KCFLlcY3FUIfBwFsVira%2FT2%2FmdL%2BKTn%2FHpkCBWXIWZ4KCi7Bv%2Fyup5iQfZXbVynTSpnCRiqJ8gU9VFQ2WeH7KsSMD3EYUbJco%2F16A9m5EeCNeANSZkmlBAl1I%3D",
    "preco": 507.21,
    "brand": "continental",
    "model": "powercontact",
    "size": "",
    "query_strict": "pneu 185/70R14 Continental PowerContact",
    "size_norm": "185-70-r14",
    "brand_expected": "continental",
    "line_expected": "powercontact",
    "size_ok": true,
    "free_ship": true,
    "frete": 0.0,
    "local": "",
    "vendedor": "",
    "condicao": "Novo",
    "frete_gratis": true,
    "marketplace": "mercadolivre",
    "marca": "continental",
    "data_coleta": "2025-08-11 17:19:59",
    "preco_original": null,
    "preco_desconto": 507.21,
    "desconto_pct": null,
    "shipping": {}
  },
  {
    "titulo": "Pneu Continental Aro 14 185/70r14 Powercontact 2 88h H",
    "link": "https://www.mercadolivre.com.br/pneu-continental-aro-14-18570r14-powercontact-2-88h/up/MLBU1753943274",
    "preco": 864.84,
    "brand": "continental",
    "model": "powercontact",
    "size": "",
    "query_strict": "pneu 185/70R14 Continental PowerContact",
    "size_norm": "185-70-r14",
    "brand_expected": "continental",
    "line_expected": "powercontact",
    "size_ok": true,
    "free_ship": true,
    "frete": 0.0,
    "local": "",
    "vendedor": "",
    "condicao": "Novo",
    "frete_gratis": true,
    "marketplace": "mercadolivre",
    "marca": "continental",
    "data_coleta": "2025-08-11 17:20:00",
    "preco_original": null,
    "preco_desconto": 864.84,
    "desconto_pct": null,
    "shipping": {}
  },
  {
    "titulo": "Pneu Continental Powercontact 2 185/70r14 88h Ht H",
    "link": "https://www.mercadolivre.com.br/pneu-continental-powercontact-2-18570r14-88h-ht/up/MLBU2947012287",
    "preco": 521.31,
    "brand": "continental",
    "model": "powercontact",
    "size": "",
    "query_strict": "pneu 185/70R14 Continental PowerContact",
    "size_norm": "185-70-r14",
    "brand_expected": "continental",
    "line_expected": "powercontact",
    "size_ok": true,
    "free_ship": true,
    "frete": 0.0,
    "local": "",
    "vendedor": "",
    "condicao": "Novo",
    "frete_gratis": true,
    "marketplace": "mercadolivre",
    "marca": "continental",
    "data_coleta": "2025-08-11 17:20:02",
    "preco_original": null,
    "preco_desconto": 521.31,
    "desconto_pct": null,
    "shipping": {}
  },
  {
    "titulo": "Pneu Continental Aro 14 185/70r14 Powercontact 2 88h H",
    "link": "https://www.mercadolivre.com.br/pneu-continental-aro-14-18570r14-powercontact-2-88h/up/MLBU3252447404",
    "preco": 752.73,
    "brand": "continental",
    "model": "powercontact",
    "size": "",
    "query_strict": "pneu 185/70R14 Continental PowerContact",
    "size_norm": "185-70-r14",
    "brand_expected": "continental",
    "line_expected": "powercontact",
    "size_ok": true,
    "free_ship": true,
    "frete": 0.0,
    "local": "",
    "vendedor": "",
    "condicao": "Novo",
    "frete_gratis": true,
    "marketplace": "mercadolivre",
    "marca": "continental",
    "data_coleta": "2025-08-11 17:20:04",
    "preco_original": null,
    "preco_desconto": 752.73,
    "desconto_pct": null,
    "shipping": {}
  },
  {
    "titulo": "Pneu Continental Aro R14 185/70r14 88h Powercontact 2",
    "link": "https://www.mercadolivre.com.br/pneu-continental-aro-r14-18570r14-88h-powercontact-2/up/MLBU1738675999",
    "preco": 630.99,
    "brand": "continental",
    "model": "powercontact",
    "size": "",
    "query_strict": "pneu 185/70R14 Continental PowerContact",
    "size_norm": "185-70-r14",
    "brand_expected": "continental",
    "line_expected": "powercontact",
    "size_ok": true,
    "free_ship": true,
    "frete": 0.0,
    "local": "",
    "vendedor": "",
    "condicao": "Novo",
    "frete_gratis": true,
    "marketplace": "mercadolivre",
    "marca": "continental",
    "data_coleta": "2025-08-11 17:20:05",
    "preco_original": null,
    "preco_desconto": 630.99,
    "desconto_pct": null,
    "shipping": {}
  },
  {
    "titulo": "Pneu 185/70r14 Powercontact 2 Continental 88h Aro R14",
    "link": "https://www.mercadolivre.com.br/pneu-18570r14-powercontact-2-continental-88h-aro-r14/up/MLBU1759358582",
    "preco": 630.99,
    "brand": "continental",
    "model": "powercontact",
    "size": "",
    "query_strict": "pneu 185/70R14 Continental PowerContact",
    "size_norm": "185-70-r14",
    "brand_expected": "continental",
    "line_expected": "powercontact",
    "size_ok": true,
    "free_ship": true,
    "frete": 0.0,
    "local": "",
    "vendedor": "",
    "condicao": "Novo",
    "frete_gratis": true,
    "marketplace": "mercadolivre",
    "marca": "continental",
    "data_coleta": "2025-08-11 17:20:07",
    "preco_original": null,
    "preco_desconto": 630.99,
    "desconto_pct": null,
    "shipping": {}
  },
  {
    "titulo": "Pneu 185/70r14 Continental Powercontact2 Nissan Livina H",
    "link": "https://www.mercadolivre.com.br/pneu-18570r14-continental-powercontact2-nissan-livina/up/MLBU1765791160",
    "preco": 630.99,
    "brand": "continental",
    "model": "powercontact",
    "size": "",
    "query_strict": "pneu 185/70R14 Continental PowerContact",
    "size_norm": "185-70-r14",
    "brand_expected": "continental",
    "line_expected": "powercontact",
    "size_ok": true,
    "free_ship": true,
    "frete": 0.0,
    "local": "",
    "vendedor": "",
    "condicao": "Novo",
    "frete_gratis": true,
    "marketplace": "mercadolivre",
    "marca": "continental",
    "data_coleta": "2025-08-11 17:20:08",
    "preco_original": null,
    "preco_desconto": 630.99,
    "desconto_pct": null,
    "shipping": {}
  },
  {
    "titulo": "Pneu 185/70r14 88h Powercontact 2 Continental Aro R14",
    "link": "https://www.mercadolivre.com.br/pneu-18570r14-88h-powercontact-2-continental-aro-r14/up/MLBU1755174107",
    "preco": 584.99,
    "brand": "continental",
    "model": "powercontact",
    "size": "",
    "query_strict": "pneu 185/70R14 Continental PowerContact",
    "size_norm": "185-70-r14",
    "brand_expected": "continental",
    "line_expected": "powercontact",
    "size_ok": true,
    "free_ship": true,
    "frete": 0.0,
    "local": "",
    "vendedor": "",
    "condicao": "Novo",
    "frete_gratis": true,
    "marketplace": "mercadolivre",
    "marca": "continental",
    "data_coleta": "2025-08-11 17:20:09",
    "preco_original": null,
    "preco_desconto": 584.99,
    "desconto_pct": null,
    "shipping": {}
  },
  {
    "titulo": "Pneu 185/70r14 88h Powercontact 2 Onix Prisma H",
    "link": "https://www.mercadolivre.com.br/pneu-18570r14-88h-powercontact-2-onix-prisma/up/MLBU1754414882",
    "preco": 584.99,
    "brand": "continental",
    "model": "powercontact",
    "size": "",
    "query_strict": "pneu 185/70R14 Continental PowerContact",
    "size_norm": "185-70-r14",
    "brand_expected": "continental",
    "line_expected": "powercontact",
    "size_ok": true,
    "free_ship": true,
    "frete": 0.0,
    "local": "",
    "vendedor": "",
    "condicao": "Novo",
    "frete_gratis": true,
    "marketplace": "mercadolivre",
    "marca": "continental",
    "data_coleta": "2025-08-11 17:20:11",
    "preco_original": null,
    "preco_desconto": 584.99,
    "desconto_pct": null,
    "shipping": {}
  },
  {
    "titulo": "Pneu Continental Aro 14 185/70r14 Powercontact 2 88h Onix",
    "link": "https://produto.mercadolivre.com.br/MLB-3774225101-pneu-continental-aro-14-18570r14-powercontact-2-88h-onix-_JM",
    "preco": 590.05,
    "brand": "continental",
    "model": "powercontact",
    "size": "",
    "query_strict": "pneu 185/70R14 Continental PowerContact",
    "size_norm": "185-70-r14",
    "brand_expected": "continental",
    "line_expected": "powercontact",
    "size_ok": true,
    "free_ship": true,
    "frete": 0.0,
    "local": "",
    "vendedor": "",
    "condicao": "Novo",
    "frete_gratis": true,
    "marketplace": "mercadolivre",
    "marca": "continental",
    "data_coleta": "2025-08-11 17:20:13",
    "preco_original": null,
    "preco_desconto": 590.05,
    "desconto_pct": null,
    "shipping": {}
  },
  {
    "titulo": "Pneu Continental Aro 14 Powercontact 2 185/70r14 88h T",
    "link": "https://www.mercadolivre.com.br/pneu-continental-aro-14-powercontact-2-18570r14-88h/up/MLBU2247284085",
    "preco": 566.64,
    "brand": "continental",
    "model": "powercontact",
    "size": "",
    "query_strict": "pneu 185/70R14 Continental PowerContact",
    "size_norm": "185-70-r14",
    "brand_expected": "continental",
    "line_expected": "powercontact",
    "size_ok": true,
    "free_ship": false,
    "frete": null,
    "local": "",
    "vendedor": "",
    "condicao": "Novo",
    "frete_gratis": false,
    "marketplace": "mercadolivre",
    "marca": "continental",
    "data_coleta": "2025-08-11 17:20:14",
    "preco_original": null,
    "preco_desconto": 566.64,
    "desconto_pct": null,
    "shipping": {}
  },
  {
    "titulo": "Pneu Continental 185/70 R14 88h Powercontact 2",
    "link": "https://produto.mercadolivre.com.br/MLB-2031947326-pneu-continental-18570-r14-88h-powercontact-2-_JM",
    "preco": 590.71,
    "brand": "continental",
    "model": "powercontact",
    "size": "",
    "query_strict": "pneu 185/70R14 Continental PowerContact",
    "size_norm": "185-70-r14",
    "brand_expected": "continental",
    "line_expected": "powercontact",
    "size_ok": true,
    "free_ship": true,
    "frete": 0.0,
    "local": "",
    "vendedor": "",
    "condicao": "Novo",
    "frete_gratis": true,
    "marketplace": "mercadolivre",
    "marca": "continental",
    "data_coleta": "2025-08-11 17:20:16",
    "preco_original": null,
    "preco_desconto": 590.71,
    "desconto_pct": null,
    "shipping": {}
  },
  {
    "titulo": "Pneu Continental 185/70 R14 88h Powercontact 2",
    "link": "https://produto.mercadolivre.com.br/MLB-2031941132-pneu-continental-18570-r14-88h-powercontact-2-_JM",
    "preco": 557.39,
    "brand": "continental",
    "model": "powercontact",
    "size": "",
    "query_strict": "pneu 185/70R14 Continental PowerContact",
    "size_norm": "185-70-r14",
    "brand_expected": "continental",
    "line_expected": "powercontact",
    "size_ok": true,
    "free_ship": true,
    "frete": 0.0,
    "local": "",
    "vendedor": "",
    "condicao": "Novo",
    "frete_gratis": true,
    "marketplace": "mercadolivre",
    "marca": "continental",
    "data_coleta": "2025-08-11 17:20:17",
    "preco_original": null,
    "preco_desconto": 557.39,
    "desconto_pct": null,
    "shipping": {}
  }
]